Workbook

Sheet 🤝 Client information
C11: Project scope & Set-up
N13: Contract status
C17: 1 Introduction
A18: <<< unfold +
C22: Purpose
C23: This document serves the purpose to align the project team of the client with the different internal teams at Skipr.
C25: Document set-up
C26: Please complete the tabs Client information, Mobility Program(s) to the best of your ability and at your earliest convenience.
C27: Please avoid changing the layout of this excel, as it might impact underlying formulas.
C28: Some sections might be folded, please use the '+' icon in the nav bar, next to the indication " <<< unfold + " to unfold them.
C30: Process
C31: The dedicated CSM at Skipr shares this document with the client, the client thereafter completes tabs Client information and Mobility Program(s) to the best of their ability.
C32: The tab GO LIVE planning will be completed together with the CSM.
C33: Upon completion of tab client information and Mobility Program(s), the client shares the completed excel file back to the dedicated CSM.
C34: A meeting is scheduled to review the information together.
C36: Based on the provided information, a go live planning is shaped (draft).
... C41: Thank you for taking the time to complete this questionnaire! 😊
B45: 🎯 | C45: 2 Objectives
A46: <<< unfold +
C50: 2.1 Please copy-paste your 3 main strategic business objectives
C52: Startegic Business Objectives (copy)
C53: Ensure compliance with legislastion
C54: Reduce cost linked to mobility
C55: Centralise mobility data
C56: Measure CO2 emissions | G56: My selection of 3 business objectives (paste)
C57: Attract new talent on the job market
C58: Increase available mobility options | F58: >>>
C59: Reduce workload linked to mobility
C60: Increase employee retention
C61: Provide insights to executive team
C62: Reduce car fleet
C64: 2.2 Please define at least one metric to measure the success of this project
C65: (example: X starters in the mobility program at the launch of the project)
B71: 🏢 | C71: 3 Company profile information
A72: <<< unfold +
C76: 3.1 Please complete the company information table below *
C77: Layout note: adding rows to this table is allowed (if needed) but please ensure the total # of employees sum is correct | M77: (Invoices are also send via Peppol)
C78: Name of entity * | F78: Parent entity | G78: VAT number * | H78: Street + nr. * | K78: Postal code, city * | L78: # of employees * | M78: Skipr fee invoice recipient e-mail address * | O78: PO number
B80: Mother entity =
B81: (if applicable)
P89: ='👾 RAW MAPPING'!J15
L90: =SUM(L80:L89) -> 0
C91: 3.2 Please specify the main points of contact during the project implementation phase *
C92: Layout note: adding rows to this table will not interfere with underlying formulas and is therefore allowed
C93: First name * | D93: Last name * | F93: email * | H93: Role | I93: Phone number ('+32474...)
B95: MAIN SPOC =
C108: 3.3 Please specify who needs admin access to the admin dashboard *
C109: Layout note: adding rows to this table will interfere with underlying formulas and is therefore not recommended
C110: First name * | D110: Last name * | F110: email * | H110: Role * | I110: Language * | J110: Gender * | K110: Admin access to all entities? * | L110: If no, to which entities should this admin get access? | N110: Also an employee access? * | O110: If yes, in which entity?
Q111: created
Q112: FALSE
Q113: FALSE
Q114: FALSE
Q115: FALSE
Q116: FALSE
Q117: FALSE
Q118: FALSE
Q119: FALSE
Q120: FALSE
Q121: FALSE
Q122: FALSE
Q123: FALSE
... Q126: FALSE
C128: 3.4 Please find hereunder your Skipr team contacts
C129: First name | D129: Last name | F129: email | H129: Role | J129: Phone number
D130: =iferror(vlookup(C130,'👾 RAW MAPPING'!A:D,2,FALSE)," ") | F130: =iferror(vlookup(C130,'👾 RAW MAPPING'!A:D,3,FALSE)," ") | H130: Customer Success Manager | J130: =iferror(vlookup(C130,'👾 RAW MAPPING'!A:D,4,FALSE)," ")
D131: =iferror(vlookup(C131,'👾 RAW MAPPING'!A:D,2,FALSE)," ") | F131: =iferror(vlookup(C131,'👾 RAW MAPPING'!A:D,3,FALSE)," ") | H131: Sales contact person | J131: =iferror(vlookup(C131,'👾 RAW MAPPING'!A:D,4,FALSE)," ")
D132: =iferror(vlookup(C132,'👾 RAW MAPPING'!A:D,2,FALSE)," ") | F132: =iferror(vlookup(C132,'👾 RAW MAPPING'!A:D,3,FALSE)," ") | J132: =iferror(vlookup(C132,'👾 RAW MAPPING'!A:D,4,FALSE)," ")
D133: =iferror(vlookup(C133,'👾 RAW MAPPING'!A:D,2,FALSE)," ") | F133: =iferror(vlookup(C133,'👾 RAW MAPPING'!A:D,3,FALSE)," ") | J133: =iferror(vlookup(C133,'👾 RAW MAPPING'!A:D,4,FALSE)," ")
B137: 🤝 | C137: 4 Mobility offer & expectations
A138: <<< unfold +
C142: 4.1 Please specify all mobility solutions you offer today to your employees by using the dropdown options
C143: Bike allowance | G143: Mobility in cafetaria plan
C144: Car allowance | G144: Professional travel expenses
C145: Pedestrian allowance | G145: Public transport subscriptions (third-party agreement)
C146: Bike lease | G146: 100% reimbursement of all public transport
C147: Company cars | G147: =/< 80% reimbursement for public transport other than NMBS
C151: 4.2 other mobility benefits you offer?
C156: 4.3 Company car information - only for Federal Mobility Budget
C157: Layout note: adding rows to this table is allowed (if needed) but please ensure the total sum is correct
C158: Name of entity | F158: # of company cars | G158: number of people with cash for car / car allowance | H158: Lease duration | I158: Cars going End-of-lease this year | J158: Cars going End-of-lease next year | K158: Federal Mobility Budget already live?
F171: =sum(F161:F170) -> 0 | G171: =sum(G161:G170) -> 0 | I171: =sum(I161:I170) -> 0 | J171: =sum(J161:J170) -> 0
C174: 4.4 Did you complete a mobility consultancy track linked to the federal mobility budget?
C175: 4.4.1 Do you have a mobility policy?
C176: 4.4.2 Have you made the budget calculations?
C180: Expectations for integrations and automations
C182: 4.5 Which additional features would you like to include in your offering? *
C183: Additional feature might come at additional costs. In case of questions, reach out to your sales contact person or / and consult the contract agreement.
C184: Feature | E184: Explanation | O184: Selected?
C185: Expense validation | E185: Skipr validation team validates all pending expenses/ reimbursement requests that need an additional proof/ receipt
C186: Expense validations: Additional information | E186: - What day of the month to you usually treat payroll?
E187: - When would you like Skipr to first check the pending expenses?
E188: - When would you like Skipr to check the pending expenses for a second time?
E189: - For recurring expenses, in case of an active contract, do you also require a proof of payment each month? (monthly manual workload for employee)
E190: - In case of housing cost, do you require a proof of the employee they are living within a 10km range?
E191: - Auto-approve of entire recurrence allowed after first occurence proof check
E192: - What proof are you requesting and for which type of expenses?
E194: - Question for Skipr CSM: | G194: What is the validations team mail address? | J194: teambackoffice.skipr+...@smartelia.com
C195: Single-sign on | E195: Upon login, users are redirected to a company page with the password auto-completed
C196: User data management | E196: An intergration between Skipr and your internal system to automatically create / archive users
...

Sheet 🚀 Mobility program(s)
C12: 🚀 | E12: Mobility program configuration
E17: Introduction mobility program configuration
E21: Please complete all grey fields to the best of your ability at your earliest convenience.
E22: Please do not change the layout of this template, as it might impact underlying formulas.
E23: Some sections might be folded, please use the '+' icon in the nav bar, next to the indication " <<< unfold + " to unfold them.
E24: Some grey fields might be dropdown menus, please select the cell and (if applicable) select one of the dropdown options.
E25: There is a section provided at the right to ask questions / leave comments in case of doubt ("Additional comments of client").
E26: In case you will start with multiple mobility programs, please complete one mobility program configuration per program.
E29: Thank you for taking the time to complete this questionnaire 😊
E35: Mobility program configuration (1)
P37: Additional comments of client | S37: Additional comments of Skipr
A38: <<< unfold + | E38: 1. Choose a name for the mobility program
E39: Mobility program template | J39: Please select a template >>>
E40: A default list of allowed mobilty services is proposed based on the selected mobility program template above, please customise it in column M
A41: <<< unfold + | E41: 2. Allowed mobility services | L41: Default | M41: Customise
E42: B-parking | L42: =IF(OR(L39="Federal Mobility Budget", L39="Commute", L39="professional travel"), "Yes", IF(L39="EV Charging & Fuel", "No", "")) | M42: =L42
E43: Bike leasing | L43: =IF(L39="Commute","Often",IF(L39="Federal Mobility Budget","Often",IF(OR(L39="Professional Travel",L39="EV Charging & Fuel"),"No",L39)))
E44: Bike purchase & Accessories | L44: =IF(OR(L39="Federal Mobility Budget"), "Yes", IF(OR(L39="professional travel", L39="EV Charging & Fuel", L39="Commute"), "No", "")) | M44: =L44
E45: Bike rent | L45: =IF(L39="Commute","Often",IF(L39="Federal Mobility Budget","Yes",IF(OR(L39="EV Charging & Fuel",L39="professional travel"),"No","")))
E46: Bus | L46: =IF(OR(L39="Federal Mobility Budget"), "Yes", IF(OR(L39="professional travel", L39="EV Charging & Fuel", L39="Commute"), "No", "")) | M46: =L46
E47: Car leasing (pillar 1) | L47: =IF(OR(L39="Federal Mobility Budget"), "Often", IF(OR(L39="professional travel", L39="EV Charging & Fuel", L39="Commute"), "No", ""))
E48: Car rental | L48: =IF(OR(L39="Federal Mobility Budget"), "Yes", IF(OR(L39="professional travel", L39="EV Charging & Fuel", L39="Commute"), "No", "")) | M48: =L48
E49: Car sharing | L49: =IF(OR(L39="Federal Mobility Budget", L39="professional travel"), "Yes", IF(OR(L39="EV Charging & Fuel", L39="Commute"), "No", "")) | M49: =L49
E50: Carpooling | L50: =IF(OR(L39="Federal Mobility Budget"), "Yes", IF(OR(L39="professional travel", L39="EV Charging & Fuel", L39="Commute"), "No", "")) | M50: =L50
E51: Shared bike | L51: =IF(OR(L39="Federal Mobility Budget", L39="Commute", L39="professional travel"), "Yes", IF(L39="EV Charging & Fuel", "No", "")) | M51: =L51
E52: Kickscooter | L52: =IF(OR(L39="Federal Mobility Budget", L39="Commute", L39="professional travel"), "Yes", IF(L39="EV Charging & Fuel", "No", "")) | M52: =L52
E53: Scooter | L53: =IF(OR(L39="Federal Mobility Budget"), "Yes", IF(OR(L39="professional travel", L39="EV Charging & Fuel", L39="Commute"), "No", "")) | M53: =L53
E54: Public parking | L54: =IF(OR(L39="professional travel"), "Yes", IF(OR(L39="Federal Mobility Budget", L39="EV Charging & Fuel", L39="Commute"), "No", "")) | M54: =L54
E55: Public transport tickets | L55: =IF(OR(L39="Federal Mobility Budget", L39="Commute", L39="professional travel"), "Yes", IF(L39="EV Charging & Fuel", "No", "")) | M55: =L55
E56: Public transport subscriptions | L56: =IF(OR(L39="Federal Mobility Budget", L39="Commute", L39="professional travel"), "Yes", IF(L39="EV Charging & Fuel", "No", "")) | M56: =L56
E57: Taxi | L57: =IF(OR(L39="Federal Mobility Budget", L39="professional travel"), "Yes", IF(OR(L39="EV Charging & Fuel", L39="Commute"), "No", "")) | M57: =L57
E58: Fuel stations | L58: =IF(OR(L39="Federal Mobility Budget", L39="Commute", L39="professional travel"), "No", IF(L39="EV Charging & Fuel", "Yes", "")) | M58: =L58
E59: Toll | L59: =IF(OR(L39="Federal Mobility Budget", L39="Commute", L39="professional travel"), "No", IF(L39="EV Charging & Fuel", "No", "")) | M59: =L59
E60: Housing cost | L60: =IF(OR(L39="Federal Mobility Budget"), "Yes", IF(OR(L39="professional travel", L39="EV Charging & Fuel", L39="Commute"), "No", "")) | M60: =L60
E61: If the employee lives within a radius of 10km from the usual place of work | K61: =IF((L60="Yes"),"Yes allow","")
E62: If the employee works more than 50% from home | K62: =IF((L60="Yes"),"Yes allow","")
E63: Bike allowance (click on '+' next to row 60 to configure) | L63: =IF(OR(L39="Federal Mobility Budget", L39="Commute", L39="professional travel"), "Yes", IF(L39="EV Charging & Fuel", "No", "")) | M63: =L63
E64: €/km | K64: =IF(OR(L63="Yes",L63="Often"),"0.37","") | M64: =K64
E65: Max km/ journey | K65: =IF(OR(L63="Yes",L63="Often"),"120","") | M65: =K65
E66: Allow employee to manually adapt the automatically proposed distance? | K66: =IF(OR(L63="Yes",L63="Often"),"No don't allow","")
E67: Admin validation required for all manually adapted distances? | K67: =IF(OR(L63="Yes",L63="Often"),"No auto-approved","")
E68: Car allowance (click on '+' next to row 65 to configure) | L68: =IF(OR(L39="professional travel", L39="Commute"), "Yes", IF(OR(L39="Federal Mobility Budget", L39="EV Charging & Fuel"), "No", "")) | M68: =L68
E69: €/km | K69: =IF(OR(L68="Yes",L68="Often"),"0.43","") | M69: =K69
E70: Max km/ journey | K70: =IF(OR(L68="Yes",L68="Often"),"250","") | M70: =K70
E71: Allow employee to manually adapt the automatically proposed distance? | K71: =IF(OR(L68="Yes",L68="Often"),"No don't allow","")
E72: Admin validation required for all manually adapted distances? | K72: =IF(OR(L68="Yes",L68="Often"),"No auto-approved","")
E73: Carpooling allowance (click on '+' next to row 70 to configure) | L73: =IF(L39="commute","Often",IF(L39="professional travel","Yes",IF(OR(L39="Federal Mobility Budget",L39="EV Charging & Fuel"),"No",L39)))
E74: €/km | K74: =IF(OR(L73="Yes",L73="Often"),"0.43","") | M74: =K74
E75: Max km/ journey | K75: =IF(OR(L73="Yes",L73="Often"),"250","") | M75: =K75
E76: Allow employee to manually adapt the automatically proposed distance? | K76: =IF(OR(L73="Yes",L73="Often"),"No don't allow","")
E77: Admin validation required for all manually adapted distances? | K77: =IF(OR(L73="Yes",L73="Often"),"No auto-approved","")
E78: Pedestrian allowance (click on '+' next to row 75 to configure) | L78: =IF(L39="Commute","Yes",IF(L39="Federal Mobility Budget","Often",IF(OR(L39="Professional Travel",L39="EV Charging & Fuel"),"No",L39)))
E79: €/km | K79: =IF(OR(L78="Yes",L78="Often"),"0.36","") | M79: =K79
E80: Max km/ journey | K80: =IF(OR(L78="Yes",L78="Often"),"15","") | M80: =K80
E81: Allow employee to manually adapt the automatically proposed distance? | K81: =IF(OR(L78="Yes",L78="Often"),"No don't allow","")
E82: Admin validation required for all manually adapted distances? | K82: =IF(OR(L78="Yes",L78="Often"),"No auto-approved","")
A83: <<< unfold + | E83: 3. Budget information
E84: 3.1 Will there be groups of people with the exact same budgets? | M84: Yes groups
E85: 👉 In case of CUSTOM BUDGETS, please specify the general budget behaviour hereunder:
F86: ▪️ Group name | K86: Only visible to admins | L86: N/A (Customised budgets)
F87: ▪️ Budget top-up amount | K87: Amount | L87: N/A (Custom budgets)
F88: ▪️ Budget top-up period | H88: Period
F89: ▪️ Remaining balance behaviour | I89: End of top-up period
F90: ▪️ Budget visibility | K90: Hide budget for employee
F91: ▪️ pro rata | G91: pro-rated amount for the first budget period
F92: ▪️ Mobility card | H92: Allowed?
F93: ▪️ Refunds | K93: allowed?
E94: 👉 In case of GROUPS, please specify the group budget behaviour hereunder:
E95: Group name | G95: Budget top-up | H95: Budget top-up | I95: Remaining | J95: Hide budget | K95: Pro rata | L95: Mobility card | M95: Refunds
E96: Only visible to admins | G96: amount (€) | H96: period | I96: budget end of period | J96: for the employee | K96: First budget top-up | L96: allowed? | M96: allowed?
A105: <<< unfold + | E105: 4. Additional information
E106: 4.1 Geographical area | J106: where can the budget be spent
E107: 4.2 Eligibility | K107: Number of eligible employees
E108: 4.3 Starters population | J108: Estimated number of starters
E109: 4.4 Go live - Invitation date | H109: First active employee accounts (estimation) | K109: Format = DD/MM/YYYY >
E110: 4.5 Budget start date | H110: Often on the same day as the GO LIVE | K110: Format = DD/MM/YYYY >
E111: Determines the moment the first employee(s) become eligible and their budget top-up starts
E112: 4.6 Reimbursements private card expenses | I112: Can employees ask for refunds for the selected services
E113: If yes, the proof attached to the refunds are checked by ...
E114: If yes, but only on some services, please specify hereunder.
E117: 4.7 Mobility payment cards | H117: Will your employees in this program benefit from a physical mobility card
E118: 4.8 Declaration of honor | G118: Add a declaration of honor your employees have to read and accept the first time connecting
E119: If yes, please contact your CSM to receive a standard "Federal Mobility Budget - Declaration of Honor"
E120: customise it to your liking and forward it back to them.
E125: In case you will start with multiple mobility programs, please complete one mobility program configuration per program.
E126: In case groups of employees will get access to multiple mobility programs, please use the same group name as mentioned in the previous mobility program.
E129: Mobility program configuration (2)
P131: Additional comments of client | S131: Additional comments of Skipr
A132: <<< unfold + | E132: 1. Choose a name for the mobility program
E133: Mobility program template | J133: Please select a template >>>
E134: A default list of allowed mobilty services is proposed based on the selected mobility program template above, please customise it in column M
A135: <<< unfold + | E135: 2. Allowed mobility services | L135: Default | M135: Customise
E136: B-parking | L136: =IF(OR(L133="Federal Mobility Budget", L133="Commute", L133="professional travel"), "Yes", IF(L133="EV Charging & Fuel", "No", "")) | M136: =L136
E137: Bike leasing | L137: =IF(L133="Commute","Often",IF(L133="Federal Mobility Budget","Often",IF(OR(L133="Professional Travel",L133="EV Charging & Fuel"),"No",L133)))
E138: Bike purchase & Accessories | L138: =IF(OR(L133="Federal Mobility Budget"), "Yes", IF(OR(L133="professional travel", L133="EV Charging & Fuel", L133="Commute"), "No", "")) | M138: =L138
E139: Bike rent | L139: =IF(L133="Commute","Often",IF(L133="Federal Mobility Budget","Yes",IF(OR(L133="EV Charging & Fuel",L133="professional travel"),"No","")))
E140: Bus | L140: =IF(OR(L133="Federal Mobility Budget"), "Yes", IF(OR(L133="professional travel", L133="EV Charging & Fuel", L133="Commute"), "No", "")) | M140: =L140
E141: Car leasing (pillar 1) | L141: =IF(OR(L133="Federal Mobility Budget"), "Often", IF(OR(L133="professional travel", L133="EV Charging & Fuel", L133="Commute"), "No", ""))
E142: Car rental | L142: =IF(OR(L133="Federal Mobility Budget"), "Yes", IF(OR(L133="professional travel", L133="EV Charging & Fuel", L133="Commute"), "No", "")) | M142: =L142
E143: Car sharing | L143: =IF(OR(L133="Federal Mobility Budget", L133="professional travel"), "Yes", IF(OR(L133="EV Charging & Fuel", L133="Commute"), "No", "")) | M143: =L143
...

Sheet 📢 GO LIVE planning
C12: 📢 | D12: Communication plan
D17: Introduction communication plan
D18: In order to guarantee a successful launch of the mobility budget within your company, a well-throughout communication plan is needed.
D19: Implementing a new mobility policy and introducing a new mobility tool comes with it's complexity, but if you follow the ADKAR model, it becomes easy!
D23: ADKAR model, what's that?
D24: During the implementation phase, there are different stakeholders that need to receive information.
D25: The ADKAR model ensures the right people receive the right information at the right time.
D27: ADKAR stands for Awareness, Desire, Knowledge, Ability, Reinforcement.
D28: Based on the information you provided in the tab "Mobility Program", we can now start building your communication plan.
D30: Please find hereunder a communication plan proposal, based on your GO LIVE date.
D31: This is a draft, dates might fall in the weekend and will have to be rescheduled.
B34: Your tailor-made communication plan
B38: 🎯 | C38: Mobility Program | F38: ='🚀 Mobility program(s)'!I38
C39: GO LIVE date | F39: ='🚀 Mobility program(s)'!M109
B42: Awareness | F42: Desire | J42: Knowledge & Ability | N42: Reinforcement
B43: Once you know what you want to offer to your employees and your mobility policy draft is getting finalized, we can start the communication towards your employees. This is the awareness phase. Skipr creates a custom slidedeck based on your policy and takes care of the communication during an online info session. This session can be recorded for later purposes, it is therefore important that the meeting invites are sent out by the client (not by Skipr) so the recording automatically arrives in the mailbox of the client after the meeting has ended. | F43: After the info session, your employees are well-informed about the mobility policy / legislation / employee benefit. In case the benefit is the Mobility Budget, this is the phase eligible employees have the time to inform HR about their interest to join the FMB (at the end of their current lease). The mobility budget amount is communicated to them individually and a contract addendum is shared (and signed) with those who can opt in. It is recommended to keep a list of interested employees, so they remain on your radar. | J43: During this phase, Skipr ensures all stakeholders are well-informed on the processes that come with the tool. Admins receive an admin training one week before the GO LIVE Employees receive an employee user training on the day they start receiving the benefit => this marks the GO LIVE date These sessions can be recorded for later purposes, it is therefore important that these sessions are sent out by the client (not by Skipr) so the recording automatically arrives in the mailbox of the client after the meeting has ended. | N43: To ensure your employees and your admins receive the best support, please make sure to share the following documents and hyperlinks with your company.
F54: Communication Package available upon request | J54: ADMIN TRAINING (meeting) | M54: =M59-7 -> -7 | N54: Info session slidedeck
B55: Info session: | N55: Info session recording
B56: 1) Slidedeck ready | E56: =E57-14 -> -58 | F56: Onepagers | J56: User training: | N56: User guide
B57: 2) Meeting invite sent out | E57: =E58-14 -> -44 | F57: Email templates | J57: 1) Slidedeck ready | M57: =M59-14 -> -14 | N57: User training recording
B58: 3) INFO SESSION (meeting) | E58: =F39-30 -> -30 | F58: user guides | J58: 2) Meeting invite sent out | M58: =M59-14 -> -14 | N58: Your dedicated CSM contact | P58: ='🤝 Client information'!F130
F59: Informative videos | J59: 3) USER TRAINING (meeting) | M59: =F39 | N59: Dashboard URL | P59: https://move.ayvens.com/
B60: Slidedeck shared with employees | E60: =E57 -> -44 | F60: etc. | N60: FAQ pages employees | P60: https://aldmove.zendesk.com/hc/en-us/categories/20561192896018-Employee
B61: Recording of info session available on intranet | E61: =E60+2 -> -42 | J61: Slidedeck shared with employees | M61: =F39 | N61: FAQ pages admins | P61: https://aldmove.zendesk.com/hc/en-us/categories/20561171188242-Admin
J62: Recording of user training available on intranet | M62: =F39+2 -> 2 | N62: Direct support | P62: https://aldmove.zendesk.com/hc/nl-be/requests/new
B64: +/- 1 to 2 months prior to GO LIVE | F64: Duration = +/- 3 weeks | J64: GO LIVE | N64: Hypercare phase

Sheet ✅ KYC documents
B12: ✅ | D12: KYC status check
D16: KYC : What? (Click on '+' to unfold and read more)
A17: <<< unfold +
D19: KYC stands for “Know Your Customer” and refers to the regulatory procedures that banks and other regulated institutions must follow.
D20: Under European and national legislation, the process verifies the identity of a customer (legal or natural person)
D21: by reviewing official documents such as an ID card, passport, proof of address, or company documents (e.g. articles of association, Kbis).
D23: As Skipr acts as a commercial agent for Treezor (the financial institution that opens payment accounts for our clients),
D24: we must demonstrate that we are in direct contact with the client requesting the account (payment account for mobility expenses)
D25: This is done by providing specific documents, as explained below.
D27: KYC : Why? (Click on '+' to unfold and read more)
A28: <<< unfold +
D30: 1. Creation of a payment account (company wallet)
D31: To allow employees to make mobility purchases, a payment account must first be created to which their mobility payment card will be linked.
D33: 2. One company wallet per entity
D34: For accounting purposes, we create one company wallet per entity using our solution. Employees are then linked to their respective entity in the platform.
D36: 3. The mobility payment card
D37: Each employee receives a mobility payment card (debit Mastercard) linked to their entity’s company wallet.
D38: The card can only be used for mobility expenses that comply with your company mobility policy.
D40: 4. KYC verification
D41: To comply with EU anti-money laundering legislation, we must complete a KYC process with our financial partner Treezor.
D42: This requires identifying the company’s ultimate beneficiary or legal representative(s) and providing identification (ID card or passport)
D43: and other documents to confirm our relationship with the client.
D47: Please collect the below documents and share them with your CSM at Skipr
D50: Your KYC tracker 👉 A tool to help you collect the KYC documents
D53: Name of entity | N53: Additional comments of client
A54: <<< unfold + | D54: ='🤝 Client information'!C80 | J54: Goal Tracker | K54: =IFERROR( ( IF(K55="Shared with Skipr",1,IF(OR(K55="Got it (not shared yet)",K55="transfer confirmation received"),0.75,IF(OR(K55="Collecting",K55="3. info shared with finance colleague"),0.25,0))) +IF(K56="Shared with Skipr",1,IF(OR(K56="Got it (not shared yet)",K56="transfer confirmation received"),0.75,IF(OR(K56="Collecting",K56="3. info shared with finance colleague"),0.25,0))) +IF(K58="Shared with Skipr",1,IF(OR(K58="Got it (not shared yet)",K58="transfer confirmation received"),0.75,IF(OR(K58="Collecting",K58="3. info shared with finance colleague"),0.25,0))) +IF(K60="Shared with Skipr",1,IF(OR(K60="Got it (not shared yet)",K60="transfer confirmation received"),0.75,IF(OR(K60="Collecting",K60="3. info shared with finance colleague"),0.25,0))) +IF(K62="Shared with Skipr",1,IF(OR(K62="Got it (not shared yet)",K62="transfer confirmation received"),0.75,IF(OR(K62="Collecting",K62="3. info shared with finance colleague"),0.25,0))) +IF(K64="Shared with Skipr",1,IF(OR(K64="Got it (not shared yet)",K64="transfer confirmation received"),0.75,IF(OR(K64="Collecting",K64="3. info shared with finance colleague"),0.25,0))) +IF(K66="Shared with Skipr",1,IF(OR(K66="Got it (not shared yet)",K66="transfer confirmation received"),0.75,IF(OR(K66="Collecting",K66="3. info shared with finance colleague"),0.25,0))) +IF(K68="Shared with Skipr",1,IF(OR(K68="Got it (not shared yet)",K68="transfer confirmation received"),0.75,IF(OR(K68="Collecting",K68="3. info shared with finance colleague"),0.25,0))) +IF(K70="Shared with Skipr",1,IF(OR(K70="Got it (not shared yet)",K70="transfer confirmation received"),0.75,IF(OR(K70="Collecting",K70="info shared with finance colleague"),0.25,0))) +IF(K71="Shared with Skipr",1,IF(OR(K71="Got it (not shared yet)",K71="transfer confirmation received"),0.75,IF(OR(K71="Collecting",K71="3. info shared with finance colleague"),0.25,0))) +IF(K76="Shared with Skipr",1,IF(OR(K76="Got it (not shared yet)",K76="transfer confirmation received"),0.75,IF(OR(K76="Collecting",K76="3. info shared with finance colleague"),0.25,0))) +IF(K81="5. Skipr informed of Transfer",1,IF(OR(K81="Got it (not shared yet)",K81="transfer confirmation received"),0.75,IF(OR(K81="Collecting",K81="3. info shared with finance colleague"),0.25,0))) ) / ( COUNTIF(K55,"<>N/A")+COUNTIF(K56,"<>N/A")+COUNTIF(K58,"<>N/A")+COUNTIF(K60,"<>N/A")+COUNTIF(K62,"<>N/A")+COUNTIF(K64,"<>N/A")+COUNTIF(K66,"<>N/A")+COUNTIF(K68,"<>N/A")+COUNTIF(K70,"<>N/A")+COUNTIF(K71,"<>N/A")+COUNTIF(K76,"<>N/A")+COUNTIF(K81,"<>N/A") ) ,0) -> 0.22916667
D55: - Constitution document | K55: Shared with Skipr
D56: - KBO document (less than 3 months old) | K56: Got it (not shared yet)
D57: 💡 Please download KBO via this URL: https://kbopub.economie.fgov.be/kbopub/zoeknummerform.html?lang=nl
D58: - Annual report J-1 | K58: Shared with Skipr
D59: 💡 Scroll down on the KBO document to find the hyperlinks to the annual report J-1
D60: - Signed Statuts | K60: not started
D61: 💡 Please download via this URL: https://statuts.notaire.be/stapor_v1/search
D62: - UBO register (less than 3 months old) | K62: not started
E63: 1) Is your company owned by a listed company?
E64: 1.1) If yes, please provide a proof that the parent entity is listed. | K64: not started
D65: 💡 | E65: Proof can be a screenshot of the Google search result : "Stock Price (PARENT ENTITY NAME)"
E66: 1.2) If no, please provide the UBO of the parent entity. | K66: not started
E67: 2) Is your company (partially) owned by a non-listed company?
E68: 2.1) If yes, please provide the UBO of that company | K68: not started
E69: 3) Is your company (partially) owned by individuals with more than 25% voting rights?
E70: 3.1) If yes, please provide the ID card(s) of the beneficiaries with +25% of voting rights | K70: not started
D71: - ID Card of Legal representative as mentioned on the KBO | K71: not started
D72: Please confirm that the card meets all the requirments | J72: Front and back
J73: High quality
J74: In color
J75: All corners visible on the picture
D76: - ID Card (if any) of individuals with +25% voting rights, as mentioned on the UBO | K76: not started
D77: Please confirm that the card meets all the requirments | J77: Front and back
J78: High quality
J79: In color
J80: All corners visible on the picture
D81: SEPA transfer | K81: 1. no info received yet
A82: <<< unfold + | D82: ='🤝 Client information'!C81 | J82: Goal Tracker | K82: =IFERROR( ( IF(K83="Shared with Skipr",1,IF(OR(K83="Got it (not shared yet)",K83="transfer confirmation received"),0.75,IF(OR(K83="Collecting",K83="3. info shared with finance colleague"),0.25,0))) +IF(K84="Shared with Skipr",1,IF(OR(K84="Got it (not shared yet)",K84="transfer confirmation received"),0.75,IF(OR(K84="Collecting",K84="3. info shared with finance colleague"),0.25,0))) +IF(K86="Shared with Skipr",1,IF(OR(K86="Got it (not shared yet)",K86="transfer confirmation received"),0.75,IF(OR(K86="Collecting",K86="3. info shared with finance colleague"),0.25,0))) +IF(K88="Shared with Skipr",1,IF(OR(K88="Got it (not shared yet)",K88="transfer confirmation received"),0.75,IF(OR(K88="Collecting",K88="3. info shared with finance colleague"),0.25,0))) +IF(K90="Shared with Skipr",1,IF(OR(K90="Got it (not shared yet)",K90="transfer confirmation received"),0.75,IF(OR(K90="Collecting",K90="3. info shared with finance colleague"),0.25,0))) +IF(K92="Shared with Skipr",1,IF(OR(K92="Got it (not shared yet)",K92="transfer confirmation received"),0.75,IF(OR(K92="Collecting",K92="3. info shared with finance colleague"),0.25,0))) +IF(K94="Shared with Skipr",1,IF(OR(K94="Got it (not shared yet)",K94="transfer confirmation received"),0.75,IF(OR(K94="Collecting",K94="3. info shared with finance colleague"),0.25,0))) +IF(K96="Shared with Skipr",1,IF(OR(K96="Got it (not shared yet)",K96="transfer confirmation received"),0.75,IF(OR(K96="Collecting",K96="3. info shared with finance colleague"),0.25,0))) +IF(K98="Shared with Skipr",1,IF(OR(K98="Got it (not shared yet)",K98="transfer confirmation received"),0.75,IF(OR(K98="Collecting",K98="info shared with finance colleague"),0.25,0))) +IF(K99="Shared with Skipr",1,IF(OR(K99="Got it (not shared yet)",K99="transfer confirmation received"),0.75,IF(OR(K99="Collecting",K99="3. info shared with finance colleague"),0.25,0))) +IF(K104="Shared with Skipr",1,IF(OR(K104="Got it (not shared yet)",K104="transfer confirmation received"),0.75,IF(OR(K104="Collecting",K104="3. info shared with finance colleague"),0.25,0))) +IF(K109="5. Skipr informed of Transfer",1,IF(OR(K109="Got it (not shared yet)",K109="transfer confirmation received"),0.75,IF(OR(K109="Collecting",K109="3. info shared with finance colleague"),0.25,0))) ) / ( COUNTIF(K83,"<>N/A")+COUNTIF(K84,"<>N/A")+COUNTIF(K86,"<>N/A")+COUNTIF(K88,"<>N/A")+COUNTIF(K90,"<>N/A")+COUNTIF(K92,"<>N/A")+COUNTIF(K94,"<>N/A")+COUNTIF(K96,"<>N/A")+COUNTIF(K98,"<>N/A")+COUNTIF(K99,"<>N/A")+COUNTIF(K104,"<>N/A")+COUNTIF(K109,"<>N/A") ) ,0) -> 0
D83: - Constitution document | K83: not started
D84: - KBO document (less than 3 months old) | K84: not started
D85: 💡 Please download KBO via this URL: https://kbopub.economie.fgov.be/kbopub/zoeknummerform.html?lang=nl
D86: - Annual report J-1 | K86: not started
D87: 💡 Scroll down on the KBO document to find the hyperlinks to the annual report J-1
D88: - Signed Statuts | K88: not started
D89: 💡 Please download via this URL: https://statuts.notaire.be/stapor_v1/search
D90: - UBO register (less than 3 months old) | K90: not started
E91: 1) Is your company owned by a listed company?
E92: 1.1) If yes, please provide a proof that the parent entity is listed. | K92: not started
D93: 💡 | E93: Proof can be a screenshot of the Google search result : "Stock Price (PARENT ENTITY NAME)"
E94: 1.2) If no, please provide the UBO of the parent entity. | K94: not started
E95: 2) Is your company (partially) owned by a non-listed company?
E96: 2.1) If yes, please provide the UBO of that company | K96: not started
E97: 3) Is your company (partially) owned by individuals with more than 25% voting rights?
E98: 3.1) If yes, please provide the ID card(s) of the beneficiaries with +25% of voting rights | K98: not started
D99: - ID Card of Legal representative as mentioned on the KBO | K99: not started
D100: Please confirm that the card meets all the requirments | J100: Front and back
J101: High quality
J102: In color
J103: All corners visible on the picture
D104: - ID Card (if any) of individuals with +25% voting rights, as mentioned on the UBO | K104: not started
D105: Please confirm that the card meets all the requirments | J105: Front and back
J106: High quality
J107: In color
J108: All corners visible on the picture
D109: SEPA transfer | K109: 1. no info received yet
A110: <<< unfold + | D110: ='🤝 Client information'!C82 | J110: Goal Tracker | K110: =IFERROR( ( IF(K111="Shared with Skipr",1,IF(OR(K111="Got it (not shared yet)",K111="transfer confirmation received"),0.75,IF(OR(K111="Collecting",K111="3. info shared with finance colleague"),0.25,0))) +IF(K112="Shared with Skipr",1,IF(OR(K112="Got it (not shared yet)",K112="transfer confirmation received"),0.75,IF(OR(K112="Collecting",K112="3. info shared with finance colleague"),0.25,0))) +IF(K114="Shared with Skipr",1,IF(OR(K114="Got it (not shared yet)",K114="transfer confirmation received"),0.75,IF(OR(K114="Collecting",K114="3. info shared with finance colleague"),0.25,0))) +IF(K116="Shared with Skipr",1,IF(OR(K116="Got it (not shared yet)",K116="transfer confirmation received"),0.75,IF(OR(K116="Collecting",K116="3. info shared with finance colleague"),0.25,0))) +IF(K118="Shared with Skipr",1,IF(OR(K118="Got it (not shared yet)",K118="transfer confirmation received"),0.75,IF(OR(K118="Collecting",K118="3. info shared with finance colleague"),0.25,0))) +IF(K120="Shared with Skipr",1,IF(OR(K120="Got it (not shared yet)",K120="transfer confirmation received"),0.75,IF(OR(K120="Collecting",K120="3. info shared with finance colleague"),0.25,0))) +IF(K122="Shared with Skipr",1,IF(OR(K122="Got it (not shared yet)",K122="transfer confirmation received"),0.75,IF(OR(K122="Collecting",K122="3. info shared with finance colleague"),0.25,0))) +IF(K124="Shared with Skipr",1,IF(OR(K124="Got it (not shared yet)",K124="transfer confirmation received"),0.75,IF(OR(K124="Collecting",K124="3. info shared with finance colleague"),0.25,0))) +IF(K126="Shared with Skipr",1,IF(OR(K126="Got it (not shared yet)",K126="transfer confirmation received"),0.75,IF(OR(K126="Collecting",K126="info shared with finance colleague"),0.25,0))) +IF(K127="Shared with Skipr",1,IF(OR(K127="Got it (not shared yet)",K127="transfer confirmation received"),0.75,IF(OR(K127="Collecting",K127="3. info shared with finance colleague"),0.25,0))) +IF(K132="Shared with Skipr",1,IF(OR(K132="Got it (not shared yet)",K132="transfer confirmation received"),0.75,IF(OR(K132="Collecting",K132="3. info shared with finance colleague"),0.25,0))) +IF(K137="5. Skipr informed of Transfer",1,IF(OR(K137="Got it (not shared yet)",K137="transfer confirmation received"),0.75,IF(OR(K137="Collecting",K137="3. info shared with finance colleague"),0.25,0))) ) / ( COUNTIF(K111,"<>N/A")+COUNTIF(K112,"<>N/A")+COUNTIF(K114,"<>N/A")+COUNTIF(K116,"<>N/A")+COUNTIF(K118,"<>N/A")+COUNTIF(K120,"<>N/A")+COUNTIF(K122,"<>N/A")+COUNTIF(K124,"<>N/A")+COUNTIF(K126,"<>N/A")+COUNTIF(K127,"<>N/A")+COUNTIF(K132,"<>N/A")+COUNTIF(K137,"<>N/A") ) ,0) -> 0
D111: - Constitution document | K111: not started
D112: - KBO document (less than 3 months old) | K112: not started
D113: 💡 Please download KBO via this URL: https://kbopub.economie.fgov.be/kbopub/zoeknummerform.html?lang=nl
D114: - Annual report J-1 | K114: not started
D115: 💡 Scroll down on the KBO document to find the hyperlinks to the annual report J-1
D116: - Signed Statuts | K116: not started
D117: 💡 Please download via this URL: https://statuts.notaire.be/stapor_v1/search
D118: - UBO register (less than 3 months old) | K118: not started
E119: 1) Is your company owned by a listed company?
E120: 1.1) If yes, please provide a proof that the parent entity is listed. | K120: not started
D121: 💡 | E121: Proof can be a screenshot of the Google search result : "Stock Price (PARENT ENTITY NAME)"
E122: 1.2) If no, please provide the UBO of the parent entity. | K122: not started
E123: 2) Is your company (partially) owned by a non-listed company?
E124: 2.1) If yes, please provide the UBO of that company | K124: not started
E125: 3) Is your company (partially) owned by individuals with more than 25% voting rights?
E126: 3.1) If yes, please provide the ID card(s) of the beneficiaries with +25% of voting rights | K126: not started
D127: - ID Card of Legal representative as mentioned on the KBO | K127: not started
D128: Please confirm that the card meets all the requirments | J128: Front and back
...

Sheet 📚 CSM overview
A2: 📚 | B2: Planhat information
A5: 💡 | B5: Attention points (to be completed by CSM): | E5: Please complete the open field below
A10: 🎛️ | B10: General client info
B11: Actionable objectives | F11: ='🤝 Client information'!G57 | I11: ='🤝 Client information'!G58 | L11: ='🤝 Client information'!G59
B12: Main SPOC | F12: ='🤝 Client information'!F95 | I12: ='🤝 Client information'!H95
D13: Contact Skipr | F13: ='🤝 Client information'!F130 | I13: ='🤝 Client information'!H130 -> Customer Success Manager
B14: Total number of employees (all entities) | F14: ='🤝 Client information'!L90 -> 0
B15: Total number of company cars (all entities) | F15: ='🤝 Client information'!F171 -> 0
D16: Total estimated number of employees at start | F16: =F37+I37+L37+O37+R37 -> 0
D17: Phyiscal cards | F17: ='🤝 Client information'!O206
B18: Smartelia Expense validation | F18: ='🤝 Client information'!O185 | G18: ='🤝 Client information'!J194 -> teambackoffice.skipr+...@smartelia.com
B19: SSO | F19: ='🤝 Client information'!O195
B20: User data management | F20: ='🤝 Client information'!O196 | G20: =IF(ISBLANK(F20),"","Keep in mind manual changes are overruled by the User Data Management")
B21: Custom Payroll Report | F21: ='🤝 Client information'!O197
B22: Payroll cut-off day | F22: ='🤝 Client information'!O199
B23: Payroll Delivery day | F23: ='🤝 Client information'!O200
D24: Pillar 3 payout company leavers | F24: ='🤝 Client information'!O201
B25: PTO management | F25: ='🤝 Client information'!O204
A27: 💸 | B27: Finance | F27: (Parent, if applicable)
B28: Parent + daughter entities | F28: ='🤝 Client information'!C80 | I28: ='🤝 Client information'!C81 | L28: ='🤝 Client information'!C82 | O28: ='🤝 Client information'!C83 | R28: ='🤝 Client information'!C84 | U28: ='🤝 Client information'!C85 | X28: ='🤝 Client information'!C86 | AA28: ='🤝 Client information'!C87 | AD28: ='🤝 Client information'!C88 | AG28: ='🤝 Client information'!$C89
B29: Invoicing recipient | F29: ='🤝 Client information'!M80 | I29: ='🤝 Client information'!M81 | L29: ='🤝 Client information'!M82 | O29: ='🤝 Client information'!M83 | R29: ='🤝 Client information'!M84 | U29: ='🤝 Client information'!M85 | X29: ='🤝 Client information'!M86 | AA29: ='🤝 Client information'!M87 | AD29: ='🤝 Client information'!M88 | AG29: ='🤝 Client information'!M89
B30: PO number | F30: ='🤝 Client information'!O80 | I30: ='🤝 Client information'!O81 | L30: ='🤝 Client information'!O82 | O30: ='🤝 Client information'!O83 | R30: ='🤝 Client information'!O84 | U30: ='🤝 Client information'!O85 | X30: ='🤝 Client information'!O86 | AA30: ='🤝 Client information'!O87 | AD30: ='🤝 Client information'!O88 | AG30: ='🤝 Client information'!O89
A32: 🚀 | B32: Mobility programs sum-up | F32: =IF(ISBLANK(F34),"","(1)") | I32: =IF(ISBLANK(I34),"","(2)") | L32: =IF(ISBLANK(L34),"","(3)") | O32: =IF(ISBLANK(O34),"","(4)") | R32: =IF(ISBLANK(R34),"","(5)")
B33: Mobility programs (default) | F33: ='🚀 Mobility program(s)'!L39 | I33: ='🚀 Mobility program(s)'!L133 | L33: ='🚀 Mobility program(s)'!L227 | O33: ='🚀 Mobility program(s)'!L321 | R33: ='🚀 Mobility program(s)'!L415
B34: Mobility Program custom name | F34: ='🚀 Mobility program(s)'!I38 | I34: ='🚀 Mobility program(s)'!I132 | L34: ='🚀 Mobility program(s)'!I226 | O34: ='🚀 Mobility program(s)'!I320 | R34: ='🚀 Mobility program(s)'!I414
B35: Requested GO LIVE | F35: ='🚀 Mobility program(s)'!M109 | G35: =IF(ISBLANK(F34),"","Go live") | I35: ='🚀 Mobility program(s)'!M203 | J35: =IF(ISBLANK(I34),"","Go live") | L35: ='🚀 Mobility program(s)'!M297 | M35: =IF(ISBLANK(L34),"","Go live") | O35: ='🚀 Mobility program(s)'!M391 | P35: =IF(ISBLANK(O34),"","Go live") | R35: ='🚀 Mobility program(s)'!M485 | S35: =IF(ISBLANK(R34),"","Go live")
B36: Eligible employees | F36: ='🚀 Mobility program(s)'!M107 | G36: =IF(ISBLANK(F34),"","eligible") | I36: ='🚀 Mobility program(s)'!M201 | J36: =IF(ISBLANK(I34),"","eligible") | L36: ='🚀 Mobility program(s)'!M295 | M36: =IF(ISBLANK(L34),"","eligible") | O36: ='🚀 Mobility program(s)'!M389 | P36: =IF(ISBLANK(O34),"","eligible") | R36: ='🚀 Mobility program(s)'!M483 | S36: =IF(ISBLANK(R34),"","eligible")
B37: Expected users at start | F37: ='🚀 Mobility program(s)'!M108 | G37: =IF(ISBLANK(F34),"","expected") | I37: ='🚀 Mobility program(s)'!M202 | J37: =IF(ISBLANK(I34),"","expected") | L37: ='🚀 Mobility program(s)'!M296 | M37: =IF(ISBLANK(L34),"","expected") | O37: ='🚀 Mobility program(s)'!M390 | P37: =IF(ISBLANK(O34),"","expected") | R37: ='🚀 Mobility program(s)'!M484 | S37: =IF(ISBLANK(R34),"","expected")
B38: Number of (mobility) services | F38: =IF(COUNTIF('🚀 Mobility program(s)'!M42:M82, "yes")>0,COUNTIF('🚀 Mobility program(s)'!M42:M82, "yes"),"") | G38: =IF(ISBLANK(F34),"","services") | I38: =IF(COUNTIF('🚀 Mobility program(s)'!M136:M176, "yes")>0,COUNTIF('🚀 Mobility program(s)'!M136:M176, "yes"),"") | J38: =IF(ISBLANK(I34),"","services") | L38: =IF(COUNTIF('🚀 Mobility program(s)'!M230:M270, "yes")>0,COUNTIF('🚀 Mobility program(s)'!M230:M270, "yes"),"") | M38: =IF(ISBLANK(L34),"","services") | O38: =IF(COUNTIF('🚀 Mobility program(s)'!M324:M364, "yes")>0,COUNTIF('🚀 Mobility program(s)'!M324:M364, "yes"),"") | P38: =IF(ISBLANK(O34),"","services") | R38: =IF(COUNTIF('🚀 Mobility program(s)'!M418:M458, "yes")>0,COUNTIF('🚀 Mobility program(s)'!M418:M458, "yes"),"") | S38: =IF(ISBLANK(R34),"","services")
B39: Number of groups | F39: =IF(COUNTA('🚀 Mobility program(s)'!E97:E104)=0, 1, COUNTA('🚀 Mobility program(s)'!E97:E104)) -> 1 | G39: =IF(ISBLANK(F34),"","groups") | I39: =IF(COUNTA('🚀 Mobility program(s)'!E191:E198)=0, 1, COUNTA('🚀 Mobility program(s)'!E191:E198)) -> 1 | J39: =IF(ISBLANK(I34),"","groups") | L39: =IF(COUNTA('🚀 Mobility program(s)'!E285:E292)=0, 1, COUNTA('🚀 Mobility program(s)'!E285:E292)) -> 1 | M39: =IF(ISBLANK(L34),"","groups") | O39: =IF(COUNTA('🚀 Mobility program(s)'!E379:E384)=0, 1, COUNTA('🚀 Mobility program(s)'!E379:E384)) -> 1 | P39: =IF(ISBLANK(O34),"","groups") | R39: =IF(COUNTA('🚀 Mobility program(s)'!E473:E480)=0, 1, COUNTA('🚀 Mobility program(s)'!E473:E480)) -> 1 | S39: =IF(ISBLANK(R34),"","groups")
B40: Geographical scope | G40: ='🚀 Mobility program(s)'!M106 | J40: ='🚀 Mobility program(s)'!M200 | M40: ='🚀 Mobility program(s)'!M294 | P40: ='🚀 Mobility program(s)'!M388 | S40: ='🚀 Mobility program(s)'!M482
B41: Reimbursement requests allowed? | G41: ='🚀 Mobility program(s)'!M112 | J41: ='🚀 Mobility program(s)'!M206 | M41: ='🚀 Mobility program(s)'!M300 | P41: ='🚀 Mobility program(s)'!M394 | S41: ='🚀 Mobility program(s)'!M488
B42: Reimbursement additional comments | F42: ='🚀 Mobility program(s)'!E115 | I42: ='🚀 Mobility program(s)'!E209 | L42: ='🚀 Mobility program(s)'!E303 | O42: ='🚀 Mobility program(s)'!E397 | R42: ='🚀 Mobility program(s)'!E491

Sheet ✍️ CSM notes
C11: ✍️ CSM notes
C15: Please write down all client specificities that might be useful for the AI agents to know.
C16: What is important to the client? Where do they deviate from the default behaviour of clients?
A18: < Read more | B18: =IF(ISBLANK(C18), "", IF(B18="", NOW(), IF(C18<>C18, NOW(), B18)))
A35: < Read more | B35: =IF(ISBLANK(C35), "", IF(B35="", NOW(), IF(C35<>C35, NOW(), B35)))
A52: < Read more | B52: =IF(ISBLANK(C52), "", IF(B52="", NOW(), IF(C52<>C52, NOW(), B52)))
A69: < Read more | B69: =IF(ISBLANK(C69), "", IF(B69="", NOW(), IF(C69<>C69, NOW(), B69)))
A86: < Read more | B86: =IF(ISBLANK(C86), "", IF(B86="", NOW(), IF(C86<>C86, NOW(), B86)))
A103: < Read more | B103: =IF(ISBLANK(C103), "", IF(B103="", NOW(), IF(C103<>C103, NOW(), B103)))
A120: < Read more | B120: =IF(ISBLANK(C120), "", IF(B120="", NOW(), IF(C120<>C120, NOW(), B120)))
A137: < Read more | B137: =IF(ISBLANK(C137), "", IF(B137="", NOW(), IF(C137<>C137, NOW(), B137)))
A154: < Read more | B154: =IF(ISBLANK(C154), "", IF(B154="", NOW(), IF(C154<>C154, NOW(), B154)))
A171: < Read more | B171: =IF(ISBLANK(C171), "", IF(B171="", NOW(), IF(C171<>C171, NOW(), B171)))
A188: < Read more | B188: =IF(ISBLANK(C188), "", IF(B188="", NOW(), IF(C188<>C188, NOW(), B188)))
A205: < Read more | B205: =IF(ISBLANK(C205), "", IF(B205="", NOW(), IF(C205<>C205, NOW(), B205)))
A222: < Read more | B222: =IF(ISBLANK(C222), "", IF(B222="", NOW(), IF(C222<>C222, NOW(), B222)))

Sheet ☑️  Validations Briefing
A2: ☑️ | B2: Skipr validations briefing
N3: Validations checked by Skipr: | O3: ='🤝 Client information'!O185
D6: Client name | F6: ='🤝 Client information'!C80
F7: First check on | G7: ='🤝 Client information'!O187 | J7: Second check on | K7: ='🤝 Client information'!O188 | N7: Payroll export day | O7: ='🤝 Client information'!O186
D8: Bulk approve recurring expenses? | F8: ='🤝 Client information'!O191
D9: Housing cost: Monthly proof of payment needed? | F9: ='🤝 Client information'!O189
D10: Housing cost: <10km range proof needed? | F10: ='🤝 Client information'!O190
D11: Validations team e-mail | F11: ='🤝 Client information'!J194 -> teambackoffice.skipr+...@smartelia.com
D12: Expected GO LIVE date | F12: ='🚀 Mobility program(s)'!M109
D13: General additional comments | F13: ='🤝 Client information'!E193
F16: 1 | H16: 2 | J16: 3 | L16: 4 | N16: 5
D17: Mobility program(s) | F17: ='🚀 Mobility program(s)'!I38 | H17: ='🚀 Mobility program(s)'!I132 | J17: ='🚀 Mobility program(s)'!I226 | L17: ='🚀 Mobility program(s)'!I320 | N17: ='🚀 Mobility program(s)'!I414
D18: Services | F18: {=IFERROR(INDEX('👾 RAW MAPPING'!$A$19:$A$55, SMALL(IF('👾 RAW MAPPING'!$A$19:$A$55<>"", ROW('👾 RAW MAPPING'!$A$19:$A$55)-ROW('👾 RAW MAPPING'!$A$19)+1), ROW(F18)-ROW(F$18)+1)), "")} | H18: {=IFERROR(INDEX('👾 RAW MAPPING'!$C$19:$C$55, SMALL(IF('👾 RAW MAPPING'!$C$19:$C$55<>"", ROW('👾 RAW MAPPING'!$C$19:$C$55)-ROW('👾 RAW MAPPING'!$C$19)+1), ROW(H18)-ROW(H$18)+1)), "")} | J18: {=IFERROR(INDEX('👾 RAW MAPPING'!$E$19:$E$55, SMALL(IF('👾 RAW MAPPING'!$E$19:$E$55<>"", ROW('👾 RAW MAPPING'!$E$19:$E$55)-ROW('👾 RAW MAPPING'!$E$19)+1), ROW(J18)-ROW(J$18)+1)), "")} | L18: {=IFERROR(INDEX('👾 RAW MAPPING'!$G$19:$G$55, SMALL(IF('👾 RAW MAPPING'!$G$19:$G$55<>"", ROW('👾 RAW MAPPING'!$G$19:$G$55)-ROW('👾 RAW MAPPING'!$G$19)+1), ROW(L18)-ROW(L$18)+1)), "")} | N18: {=IFERROR(INDEX('👾 RAW MAPPING'!$I$19:$I$55, SMALL(IF('👾 RAW MAPPING'!$I$19:$I$55<>"", ROW('👾 RAW MAPPING'!$I$19:$I$55)-ROW('👾 RAW MAPPING'!$I$19)+1), ROW(N18)-ROW(N$18)+1)), "")}
F19: {=IFERROR(INDEX('👾 RAW MAPPING'!$A$19:$A$55, SMALL(IF('👾 RAW MAPPING'!$A$19:$A$55<>"", ROW('👾 RAW MAPPING'!$A$19:$A$55)-ROW('👾 RAW MAPPING'!$A$19)+1), ROW(F19)-ROW(F$18)+1)), "")} | H19: {=IFERROR(INDEX('👾 RAW MAPPING'!$C$19:$C$55, SMALL(IF('👾 RAW MAPPING'!$C$19:$C$55<>"", ROW('👾 RAW MAPPING'!$C$19:$C$55)-ROW('👾 RAW MAPPING'!$C$19)+1), ROW(H19)-ROW(H$18)+1)), "")} | J19: {=IFERROR(INDEX('👾 RAW MAPPING'!$E$19:$E$55, SMALL(IF('👾 RAW MAPPING'!$E$19:$E$55<>"", ROW('👾 RAW MAPPING'!$E$19:$E$55)-ROW('👾 RAW MAPPING'!$E$19)+1), ROW(J19)-ROW(J$18)+1)), "")} | L19: {=IFERROR(INDEX('👾 RAW MAPPING'!$G$19:$G$55, SMALL(IF('👾 RAW MAPPING'!$G$19:$G$55<>"", ROW('👾 RAW MAPPING'!$G$19:$G$55)-ROW('👾 RAW MAPPING'!$G$19)+1), ROW(L19)-ROW(L$18)+1)), "")} | N19: {=IFERROR(INDEX('👾 RAW MAPPING'!$I$19:$I$55, SMALL(IF('👾 RAW MAPPING'!$I$19:$I$55<>"", ROW('👾 RAW MAPPING'!$I$19:$I$55)-ROW('👾 RAW MAPPING'!$I$19)+1), ROW(N19)-ROW(N$18)+1)), "")}
F20: {=IFERROR(INDEX('👾 RAW MAPPING'!$A$19:$A$55, SMALL(IF('👾 RAW MAPPING'!$A$19:$A$55<>"", ROW('👾 RAW MAPPING'!$A$19:$A$55)-ROW('👾 RAW MAPPING'!$A$19)+1), ROW(F20)-ROW(F$18)+1)), "")} | H20: {=IFERROR(INDEX('👾 RAW MAPPING'!$C$19:$C$55, SMALL(IF('👾 RAW MAPPING'!$C$19:$C$55<>"", ROW('👾 RAW MAPPING'!$C$19:$C$55)-ROW('👾 RAW MAPPING'!$C$19)+1), ROW(H20)-ROW(H$18)+1)), "")} | J20: {=IFERROR(INDEX('👾 RAW MAPPING'!$E$19:$E$55, SMALL(IF('👾 RAW MAPPING'!$E$19:$E$55<>"", ROW('👾 RAW MAPPING'!$E$19:$E$55)-ROW('👾 RAW MAPPING'!$E$19)+1), ROW(J20)-ROW(J$18)+1)), "")} | L20: {=IFERROR(INDEX('👾 RAW MAPPING'!$G$19:$G$55, SMALL(IF('👾 RAW MAPPING'!$G$19:$G$55<>"", ROW('👾 RAW MAPPING'!$G$19:$G$55)-ROW('👾 RAW MAPPING'!$G$19)+1), ROW(L20)-ROW(L$18)+1)), "")} | N20: {=IFERROR(INDEX('👾 RAW MAPPING'!$I$19:$I$55, SMALL(IF('👾 RAW MAPPING'!$I$19:$I$55<>"", ROW('👾 RAW MAPPING'!$I$19:$I$55)-ROW('👾 RAW MAPPING'!$I$19)+1), ROW(N20)-ROW(N$18)+1)), "")}
F21: {=IFERROR(INDEX('👾 RAW MAPPING'!$A$19:$A$55, SMALL(IF('👾 RAW MAPPING'!$A$19:$A$55<>"", ROW('👾 RAW MAPPING'!$A$19:$A$55)-ROW('👾 RAW MAPPING'!$A$19)+1), ROW(F21)-ROW(F$18)+1)), "")} | H21: {=IFERROR(INDEX('👾 RAW MAPPING'!$C$19:$C$55, SMALL(IF('👾 RAW MAPPING'!$C$19:$C$55<>"", ROW('👾 RAW MAPPING'!$C$19:$C$55)-ROW('👾 RAW MAPPING'!$C$19)+1), ROW(H21)-ROW(H$18)+1)), "")} | J21: {=IFERROR(INDEX('👾 RAW MAPPING'!$E$19:$E$55, SMALL(IF('👾 RAW MAPPING'!$E$19:$E$55<>"", ROW('👾 RAW MAPPING'!$E$19:$E$55)-ROW('👾 RAW MAPPING'!$E$19)+1), ROW(J21)-ROW(J$18)+1)), "")} | L21: {=IFERROR(INDEX('👾 RAW MAPPING'!$G$19:$G$55, SMALL(IF('👾 RAW MAPPING'!$G$19:$G$55<>"", ROW('👾 RAW MAPPING'!$G$19:$G$55)-ROW('👾 RAW MAPPING'!$G$19)+1), ROW(L21)-ROW(L$18)+1)), "")} | N21: {=IFERROR(INDEX('👾 RAW MAPPING'!$I$19:$I$55, SMALL(IF('👾 RAW MAPPING'!$I$19:$I$55<>"", ROW('👾 RAW MAPPING'!$I$19:$I$55)-ROW('👾 RAW MAPPING'!$I$19)+1), ROW(N21)-ROW(N$18)+1)), "")}
F22: {=IFERROR(INDEX('👾 RAW MAPPING'!$A$19:$A$55, SMALL(IF('👾 RAW MAPPING'!$A$19:$A$55<>"", ROW('👾 RAW MAPPING'!$A$19:$A$55)-ROW('👾 RAW MAPPING'!$A$19)+1), ROW(F22)-ROW(F$18)+1)), "")} | H22: {=IFERROR(INDEX('👾 RAW MAPPING'!$C$19:$C$55, SMALL(IF('👾 RAW MAPPING'!$C$19:$C$55<>"", ROW('👾 RAW MAPPING'!$C$19:$C$55)-ROW('👾 RAW MAPPING'!$C$19)+1), ROW(H22)-ROW(H$18)+1)), "")} | J22: {=IFERROR(INDEX('👾 RAW MAPPING'!$E$19:$E$55, SMALL(IF('👾 RAW MAPPING'!$E$19:$E$55<>"", ROW('👾 RAW MAPPING'!$E$19:$E$55)-ROW('👾 RAW MAPPING'!$E$19)+1), ROW(J22)-ROW(J$18)+1)), "")} | L22: {=IFERROR(INDEX('👾 RAW MAPPING'!$G$19:$G$55, SMALL(IF('👾 RAW MAPPING'!$G$19:$G$55<>"", ROW('👾 RAW MAPPING'!$G$19:$G$55)-ROW('👾 RAW MAPPING'!$G$19)+1), ROW(L22)-ROW(L$18)+1)), "")} | N22: {=IFERROR(INDEX('👾 RAW MAPPING'!$I$19:$I$55, SMALL(IF('👾 RAW MAPPING'!$I$19:$I$55<>"", ROW('👾 RAW MAPPING'!$I$19:$I$55)-ROW('👾 RAW MAPPING'!$I$19)+1), ROW(N22)-ROW(N$18)+1)), "")}
F23: {=IFERROR(INDEX('👾 RAW MAPPING'!$A$19:$A$55, SMALL(IF('👾 RAW MAPPING'!$A$19:$A$55<>"", ROW('👾 RAW MAPPING'!$A$19:$A$55)-ROW('👾 RAW MAPPING'!$A$19)+1), ROW(F23)-ROW(F$18)+1)), "")} | H23: {=IFERROR(INDEX('👾 RAW MAPPING'!$C$19:$C$55, SMALL(IF('👾 RAW MAPPING'!$C$19:$C$55<>"", ROW('👾 RAW MAPPING'!$C$19:$C$55)-ROW('👾 RAW MAPPING'!$C$19)+1), ROW(H23)-ROW(H$18)+1)), "")} | J23: {=IFERROR(INDEX('👾 RAW MAPPING'!$E$19:$E$55, SMALL(IF('👾 RAW MAPPING'!$E$19:$E$55<>"", ROW('👾 RAW MAPPING'!$E$19:$E$55)-ROW('👾 RAW MAPPING'!$E$19)+1), ROW(J23)-ROW(J$18)+1)), "")} | L23: {=IFERROR(INDEX('👾 RAW MAPPING'!$G$19:$G$55, SMALL(IF('👾 RAW MAPPING'!$G$19:$G$55<>"", ROW('👾 RAW MAPPING'!$G$19:$G$55)-ROW('👾 RAW MAPPING'!$G$19)+1), ROW(L23)-ROW(L$18)+1)), "")} | N23: {=IFERROR(INDEX('👾 RAW MAPPING'!$I$19:$I$55, SMALL(IF('👾 RAW MAPPING'!$I$19:$I$55<>"", ROW('👾 RAW MAPPING'!$I$19:$I$55)-ROW('👾 RAW MAPPING'!$I$19)+1), ROW(N23)-ROW(N$18)+1)), "")}
F24: {=IFERROR(INDEX('👾 RAW MAPPING'!$A$19:$A$55, SMALL(IF('👾 RAW MAPPING'!$A$19:$A$55<>"", ROW('👾 RAW MAPPING'!$A$19:$A$55)-ROW('👾 RAW MAPPING'!$A$19)+1), ROW(F24)-ROW(F$18)+1)), "")} | H24: {=IFERROR(INDEX('👾 RAW MAPPING'!$C$19:$C$55, SMALL(IF('👾 RAW MAPPING'!$C$19:$C$55<>"", ROW('👾 RAW MAPPING'!$C$19:$C$55)-ROW('👾 RAW MAPPING'!$C$19)+1), ROW(H24)-ROW(H$18)+1)), "")} | J24: {=IFERROR(INDEX('👾 RAW MAPPING'!$E$19:$E$55, SMALL(IF('👾 RAW MAPPING'!$E$19:$E$55<>"", ROW('👾 RAW MAPPING'!$E$19:$E$55)-ROW('👾 RAW MAPPING'!$E$19)+1), ROW(J24)-ROW(J$18)+1)), "")} | L24: {=IFERROR(INDEX('👾 RAW MAPPING'!$G$19:$G$55, SMALL(IF('👾 RAW MAPPING'!$G$19:$G$55<>"", ROW('👾 RAW MAPPING'!$G$19:$G$55)-ROW('👾 RAW MAPPING'!$G$19)+1), ROW(L24)-ROW(L$18)+1)), "")} | N24: {=IFERROR(INDEX('👾 RAW MAPPING'!$I$19:$I$55, SMALL(IF('👾 RAW MAPPING'!$I$19:$I$55<>"", ROW('👾 RAW MAPPING'!$I$19:$I$55)-ROW('👾 RAW MAPPING'!$I$19)+1), ROW(N24)-ROW(N$18)+1)), "")}
F25: {=IFERROR(INDEX('👾 RAW MAPPING'!$A$19:$A$55, SMALL(IF('👾 RAW MAPPING'!$A$19:$A$55<>"", ROW('👾 RAW MAPPING'!$A$19:$A$55)-ROW('👾 RAW MAPPING'!$A$19)+1), ROW(F25)-ROW(F$18)+1)), "")} | H25: {=IFERROR(INDEX('👾 RAW MAPPING'!$C$19:$C$55, SMALL(IF('👾 RAW MAPPING'!$C$19:$C$55<>"", ROW('👾 RAW MAPPING'!$C$19:$C$55)-ROW('👾 RAW MAPPING'!$C$19)+1), ROW(H25)-ROW(H$18)+1)), "")} | J25: {=IFERROR(INDEX('👾 RAW MAPPING'!$E$19:$E$55, SMALL(IF('👾 RAW MAPPING'!$E$19:$E$55<>"", ROW('👾 RAW MAPPING'!$E$19:$E$55)-ROW('👾 RAW MAPPING'!$E$19)+1), ROW(J25)-ROW(J$18)+1)), "")} | L25: {=IFERROR(INDEX('👾 RAW MAPPING'!$G$19:$G$55, SMALL(IF('👾 RAW MAPPING'!$G$19:$G$55<>"", ROW('👾 RAW MAPPING'!$G$19:$G$55)-ROW('👾 RAW MAPPING'!$G$19)+1), ROW(L25)-ROW(L$18)+1)), "")} | N25: {=IFERROR(INDEX('👾 RAW MAPPING'!$I$19:$I$55, SMALL(IF('👾 RAW MAPPING'!$I$19:$I$55<>"", ROW('👾 RAW MAPPING'!$I$19:$I$55)-ROW('👾 RAW MAPPING'!$I$19)+1), ROW(N25)-ROW(N$18)+1)), "")}
F26: {=IFERROR(INDEX('👾 RAW MAPPING'!$A$19:$A$55, SMALL(IF('👾 RAW MAPPING'!$A$19:$A$55<>"", ROW('👾 RAW MAPPING'!$A$19:$A$55)-ROW('👾 RAW MAPPING'!$A$19)+1), ROW(F26)-ROW(F$18)+1)), "")} | H26: {=IFERROR(INDEX('👾 RAW MAPPING'!$C$19:$C$55, SMALL(IF('👾 RAW MAPPING'!$C$19:$C$55<>"", ROW('👾 RAW MAPPING'!$C$19:$C$55)-ROW('👾 RAW MAPPING'!$C$19)+1), ROW(H26)-ROW(H$18)+1)), "")} | J26: {=IFERROR(INDEX('👾 RAW MAPPING'!$E$19:$E$55, SMALL(IF('👾 RAW MAPPING'!$E$19:$E$55<>"", ROW('👾 RAW MAPPING'!$E$19:$E$55)-ROW('👾 RAW MAPPING'!$E$19)+1), ROW(J26)-ROW(J$18)+1)), "")} | L26: {=IFERROR(INDEX('👾 RAW MAPPING'!$G$19:$G$55, SMALL(IF('👾 RAW MAPPING'!$G$19:$G$55<>"", ROW('👾 RAW MAPPING'!$G$19:$G$55)-ROW('👾 RAW MAPPING'!$G$19)+1), ROW(L26)-ROW(L$18)+1)), "")} | N26: {=IFERROR(INDEX('👾 RAW MAPPING'!$I$19:$I$55, SMALL(IF('👾 RAW MAPPING'!$I$19:$I$55<>"", ROW('👾 RAW MAPPING'!$I$19:$I$55)-ROW('👾 RAW MAPPING'!$I$19)+1), ROW(N26)-ROW(N$18)+1)), "")}
F27: {=IFERROR(INDEX('👾 RAW MAPPING'!$A$19:$A$55, SMALL(IF('👾 RAW MAPPING'!$A$19:$A$55<>"", ROW('👾 RAW MAPPING'!$A$19:$A$55)-ROW('👾 RAW MAPPING'!$A$19)+1), ROW(F27)-ROW(F$18)+1)), "")} | H27: {=IFERROR(INDEX('👾 RAW MAPPING'!$C$19:$C$55, SMALL(IF('👾 RAW MAPPING'!$C$19:$C$55<>"", ROW('👾 RAW MAPPING'!$C$19:$C$55)-ROW('👾 RAW MAPPING'!$C$19)+1), ROW(H27)-ROW(H$18)+1)), "")} | J27: {=IFERROR(INDEX('👾 RAW MAPPING'!$E$19:$E$55, SMALL(IF('👾 RAW MAPPING'!$E$19:$E$55<>"", ROW('👾 RAW MAPPING'!$E$19:$E$55)-ROW('👾 RAW MAPPING'!$E$19)+1), ROW(J27)-ROW(J$18)+1)), "")} | L27: {=IFERROR(INDEX('👾 RAW MAPPING'!$G$19:$G$55, SMALL(IF('👾 RAW MAPPING'!$G$19:$G$55<>"", ROW('👾 RAW MAPPING'!$G$19:$G$55)-ROW('👾 RAW MAPPING'!$G$19)+1), ROW(L27)-ROW(L$18)+1)), "")} | N27: {=IFERROR(INDEX('👾 RAW MAPPING'!$I$19:$I$55, SMALL(IF('👾 RAW MAPPING'!$I$19:$I$55<>"", ROW('👾 RAW MAPPING'!$I$19:$I$55)-ROW('👾 RAW MAPPING'!$I$19)+1), ROW(N27)-ROW(N$18)+1)), "")}
F28: {=IFERROR(INDEX('👾 RAW MAPPING'!$A$19:$A$55, SMALL(IF('👾 RAW MAPPING'!$A$19:$A$55<>"", ROW('👾 RAW MAPPING'!$A$19:$A$55)-ROW('👾 RAW MAPPING'!$A$19)+1), ROW(F28)-ROW(F$18)+1)), "")} | H28: {=IFERROR(INDEX('👾 RAW MAPPING'!$C$19:$C$55, SMALL(IF('👾 RAW MAPPING'!$C$19:$C$55<>"", ROW('👾 RAW MAPPING'!$C$19:$C$55)-ROW('👾 RAW MAPPING'!$C$19)+1), ROW(H28)-ROW(H$18)+1)), "")} | J28: {=IFERROR(INDEX('👾 RAW MAPPING'!$E$19:$E$55, SMALL(IF('👾 RAW MAPPING'!$E$19:$E$55<>"", ROW('👾 RAW MAPPING'!$E$19:$E$55)-ROW('👾 RAW MAPPING'!$E$19)+1), ROW(J28)-ROW(J$18)+1)), "")} | L28: {=IFERROR(INDEX('👾 RAW MAPPING'!$G$19:$G$55, SMALL(IF('👾 RAW MAPPING'!$G$19:$G$55<>"", ROW('👾 RAW MAPPING'!$G$19:$G$55)-ROW('👾 RAW MAPPING'!$G$19)+1), ROW(L28)-ROW(L$18)+1)), "")} | N28: {=IFERROR(INDEX('👾 RAW MAPPING'!$I$19:$I$55, SMALL(IF('👾 RAW MAPPING'!$I$19:$I$55<>"", ROW('👾 RAW MAPPING'!$I$19:$I$55)-ROW('👾 RAW MAPPING'!$I$19)+1), ROW(N28)-ROW(N$18)+1)), "")}
F29: {=IFERROR(INDEX('👾 RAW MAPPING'!$A$19:$A$55, SMALL(IF('👾 RAW MAPPING'!$A$19:$A$55<>"", ROW('👾 RAW MAPPING'!$A$19:$A$55)-ROW('👾 RAW MAPPING'!$A$19)+1), ROW(F29)-ROW(F$18)+1)), "")} | H29: {=IFERROR(INDEX('👾 RAW MAPPING'!$C$19:$C$55, SMALL(IF('👾 RAW MAPPING'!$C$19:$C$55<>"", ROW('👾 RAW MAPPING'!$C$19:$C$55)-ROW('👾 RAW MAPPING'!$C$19)+1), ROW(H29)-ROW(H$18)+1)), "")} | J29: {=IFERROR(INDEX('👾 RAW MAPPING'!$E$19:$E$55, SMALL(IF('👾 RAW MAPPING'!$E$19:$E$55<>"", ROW('👾 RAW MAPPING'!$E$19:$E$55)-ROW('👾 RAW MAPPING'!$E$19)+1), ROW(J29)-ROW(J$18)+1)), "")} | L29: {=IFERROR(INDEX('👾 RAW MAPPING'!$G$19:$G$55, SMALL(IF('👾 RAW MAPPING'!$G$19:$G$55<>"", ROW('👾 RAW MAPPING'!$G$19:$G$55)-ROW('👾 RAW MAPPING'!$G$19)+1), ROW(L29)-ROW(L$18)+1)), "")} | N29: {=IFERROR(INDEX('👾 RAW MAPPING'!$I$19:$I$55, SMALL(IF('👾 RAW MAPPING'!$I$19:$I$55<>"", ROW('👾 RAW MAPPING'!$I$19:$I$55)-ROW('👾 RAW MAPPING'!$I$19)+1), ROW(N29)-ROW(N$18)+1)), "")}
F30: {=IFERROR(INDEX('👾 RAW MAPPING'!$A$19:$A$55, SMALL(IF('👾 RAW MAPPING'!$A$19:$A$55<>"", ROW('👾 RAW MAPPING'!$A$19:$A$55)-ROW('👾 RAW MAPPING'!$A$19)+1), ROW(F30)-ROW(F$18)+1)), "")} | H30: {=IFERROR(INDEX('👾 RAW MAPPING'!$C$19:$C$55, SMALL(IF('👾 RAW MAPPING'!$C$19:$C$55<>"", ROW('👾 RAW MAPPING'!$C$19:$C$55)-ROW('👾 RAW MAPPING'!$C$19)+1), ROW(H30)-ROW(H$18)+1)), "")} | J30: {=IFERROR(INDEX('👾 RAW MAPPING'!$E$19:$E$55, SMALL(IF('👾 RAW MAPPING'!$E$19:$E$55<>"", ROW('👾 RAW MAPPING'!$E$19:$E$55)-ROW('👾 RAW MAPPING'!$E$19)+1), ROW(J30)-ROW(J$18)+1)), "")} | L30: {=IFERROR(INDEX('👾 RAW MAPPING'!$G$19:$G$55, SMALL(IF('👾 RAW MAPPING'!$G$19:$G$55<>"", ROW('👾 RAW MAPPING'!$G$19:$G$55)-ROW('👾 RAW MAPPING'!$G$19)+1), ROW(L30)-ROW(L$18)+1)), "")} | N30: {=IFERROR(INDEX('👾 RAW MAPPING'!$I$19:$I$55, SMALL(IF('👾 RAW MAPPING'!$I$19:$I$55<>"", ROW('👾 RAW MAPPING'!$I$19:$I$55)-ROW('👾 RAW MAPPING'!$I$19)+1), ROW(N30)-ROW(N$18)+1)), "")}
... F36: {=IFERROR(INDEX('👾 RAW MAPPING'!$A$19:$A$55, SMALL(IF('👾 RAW MAPPING'!$A$19:$A$55<>"", ROW('👾 RAW MAPPING'!$A$19:$A$55)-ROW('👾 RAW MAPPING'!$A$19)+1), ROW(F36)-ROW(F$18)+1)), "")} | H36: {=IFERROR(INDEX('👾 RAW MAPPING'!$C$19:$C$55, SMALL(IF('👾 RAW MAPPING'!$C$19:$C$55<>"", ROW('👾 RAW MAPPING'!$C$19:$C$55)-ROW('👾 RAW MAPPING'!$C$19)+1), ROW(H36)-ROW(H$18)+1)), "")} | J36: {=IFERROR(INDEX('👾 RAW MAPPING'!$E$19:$E$55, SMALL(IF('👾 RAW MAPPING'!$E$19:$E$55<>"", ROW('👾 RAW MAPPING'!$E$19:$E$55)-ROW('👾 RAW MAPPING'!$E$19)+1), ROW(J36)-ROW(J$18)+1)), "")} | L36: {=IFERROR(INDEX('👾 RAW MAPPING'!$G$19:$G$55, SMALL(IF('👾 RAW MAPPING'!$G$19:$G$55<>"", ROW('👾 RAW MAPPING'!$G$19:$G$55)-ROW('👾 RAW MAPPING'!$G$19)+1), ROW(L36)-ROW(L$18)+1)), "")} | N36: {=IFERROR(INDEX('👾 RAW MAPPING'!$I$19:$I$55, SMALL(IF('👾 RAW MAPPING'!$I$19:$I$55<>"", ROW('👾 RAW MAPPING'!$I$19:$I$55)-ROW('👾 RAW MAPPING'!$I$19)+1), ROW(N36)-ROW(N$18)+1)), "")}
D37: Reimbursements allowed? | F37: ='🚀 Mobility program(s)'!M112 | H37: ='🚀 Mobility program(s)'!M206 | J37: ='🚀 Mobility program(s)'!M300 | L37: ='🚀 Mobility program(s)'!M394 | N37: ='🚀 Mobility program(s)'!M488
D38: Proof is checked by? | F38: ='🚀 Mobility program(s)'!M113 | H38: ='🚀 Mobility program(s)'!M207 | J38: ='🚀 Mobility program(s)'!M301 | L38: ='🚀 Mobility program(s)'!M395 | N38: ='🚀 Mobility program(s)'!M489
D39: Additional comments per program? | F39: ='🚀 Mobility program(s)'!E115 | H39: ='🚀 Mobility program(s)'!E209 | J39: ='🚀 Mobility program(s)'!E303 | L39: ='🚀 Mobility program(s)'!E397 | N39: ='🚀 Mobility program(s)'!E491
F47: Updated controller rules (these overrule the above mentioned control rules) | O47: Date stamp
D48: Additional comments of CSM | O48: =IF(ISBLANK(F48), "", IF(O48="", NOW(), IF(F48<>F48, NOW(), O48)))
O49: =IF(ISBLANK(F49), "", IF(O49="", NOW(), IF(F49<>F49, NOW(), O49)))
O50: =IF(ISBLANK(F50), "", IF(O50="", NOW(), IF(F50<>F50, NOW(), O50)))
O51: =IF(ISBLANK(F51), "", IF(O51="", NOW(), IF(F51<>F51, NOW(), O51)))
O52: =IF(ISBLANK(F52), "", IF(O52="", NOW(), IF(F52<>F52, NOW(), O52)))
O53: =IF(ISBLANK(F53), "", IF(O53="", NOW(), IF(F53<>F53, NOW(), O53)))

Sheet 👥 Admin creation file
A1: first_name | B1: last_name | C1: email | D1: phone_number | E1: phone_number_country_code | F1: language | G1: gender | H1: date_of_birth | I1: place_of_birth | J1: country_of_birth | K1: nationality | L1: job_title | M1: role | N1: start_on | O1: address__street | P1: address__postal_code | Q1: address__city | R1: address__country_code | S1: new_gen | T1: group_name | U1: invite_on | V1: use_physical_card | W1: internal_payroll_id | X1: cost_center
A2: {=IFERROR(INDEX('👾 RAW MAPPING'!$A$59:$A$73, SMALL(IF('👾 RAW MAPPING'!$A$59:$A$73<>"", ROW('👾 RAW MAPPING'!$A$59:$A$73)-ROW('👾 RAW MAPPING'!$A$59)+1), ROW(A2)-ROW(A$2)+1)), "")} | B2: {=IFERROR(INDEX('👾 RAW MAPPING'!$B$59:$B$73, SMALL(IF('👾 RAW MAPPING'!$B$59:$B$73<>"", ROW('👾 RAW MAPPING'!$B$59:$B$73)-ROW('👾 RAW MAPPING'!$B$59)+1), ROW(B2)-ROW(B$2)+1)), "")} | C2: {=IFERROR(INDEX('👾 RAW MAPPING'!$C$59:$C$73, SMALL(IF('👾 RAW MAPPING'!$C$59:$C$73<>"", ROW('👾 RAW MAPPING'!$C$59:$C$73)-ROW('👾 RAW MAPPING'!$C$59)+1), ROW(C2)-ROW(C$2)+1)), "")} | F2: {=IFERROR(INDEX('👾 RAW MAPPING'!$F$59:$F$73, SMALL(IF('👾 RAW MAPPING'!$F$59:$F$73<>"", ROW('👾 RAW MAPPING'!$F$59:$F$73)-ROW('👾 RAW MAPPING'!$F$59)+1), ROW(F2)-ROW(F$2)+1)), "")} | G2: {=IFERROR(INDEX('👾 RAW MAPPING'!$G$59:$G$73, SMALL(IF('👾 RAW MAPPING'!$G$59:$G$73<>"", ROW('👾 RAW MAPPING'!$G$59:$G$73)-ROW('👾 RAW MAPPING'!$G$59)+1), ROW(G2)-ROW(G$2)+1)), "")} | M2: {=IFERROR(INDEX('👾 RAW MAPPING'!$M$59:$M$73, SMALL(IF('👾 RAW MAPPING'!$M$59:$M$73<>"", ROW('👾 RAW MAPPING'!$M$59:$M$73)-ROW('👾 RAW MAPPING'!$M$59)+1), ROW(M2)-ROW(M$2)+1)), "")} | N2: =IF(A2<>"",TODAY(),"") | S2: =IF(A2<>"","yes","") | U2: =IF(A2<>"",TODAY(),"")
A3: {=IFERROR(INDEX('👾 RAW MAPPING'!$A$59:$A$73, SMALL(IF('👾 RAW MAPPING'!$A$59:$A$73<>"", ROW('👾 RAW MAPPING'!$A$59:$A$73)-ROW('👾 RAW MAPPING'!$A$59)+1), ROW(A3)-ROW(A$2)+1)), "")} | B3: {=IFERROR(INDEX('👾 RAW MAPPING'!$B$59:$B$73, SMALL(IF('👾 RAW MAPPING'!$B$59:$B$73<>"", ROW('👾 RAW MAPPING'!$B$59:$B$73)-ROW('👾 RAW MAPPING'!$B$59)+1), ROW(B3)-ROW(B$2)+1)), "")} | C3: {=IFERROR(INDEX('👾 RAW MAPPING'!$C$59:$C$73, SMALL(IF('👾 RAW MAPPING'!$C$59:$C$73<>"", ROW('👾 RAW MAPPING'!$C$59:$C$73)-ROW('👾 RAW MAPPING'!$C$59)+1), ROW(C3)-ROW(C$2)+1)), "")} | F3: {=IFERROR(INDEX('👾 RAW MAPPING'!$F$59:$F$73, SMALL(IF('👾 RAW MAPPING'!$F$59:$F$73<>"", ROW('👾 RAW MAPPING'!$F$59:$F$73)-ROW('👾 RAW MAPPING'!$F$59)+1), ROW(F3)-ROW(F$2)+1)), "")} | G3: {=IFERROR(INDEX('👾 RAW MAPPING'!$G$59:$G$73, SMALL(IF('👾 RAW MAPPING'!$G$59:$G$73<>"", ROW('👾 RAW MAPPING'!$G$59:$G$73)-ROW('👾 RAW MAPPING'!$G$59)+1), ROW(G3)-ROW(G$2)+1)), "")} | M3: {=IFERROR(INDEX('👾 RAW MAPPING'!$M$59:$M$73, SMALL(IF('👾 RAW MAPPING'!$M$59:$M$73<>"", ROW('👾 RAW MAPPING'!$M$59:$M$73)-ROW('👾 RAW MAPPING'!$M$59)+1), ROW(M3)-ROW(M$2)+1)), "")} | N3: =IF(A3<>"",TODAY(),"") | S3: =IF(A3<>"","yes","") | U3: =IF(A3<>"",TODAY(),"")
A4: {=IFERROR(INDEX('👾 RAW MAPPING'!$A$59:$A$73, SMALL(IF('👾 RAW MAPPING'!$A$59:$A$73<>"", ROW('👾 RAW MAPPING'!$A$59:$A$73)-ROW('👾 RAW MAPPING'!$A$59)+1), ROW(A4)-ROW(A$2)+1)), "")} | B4: {=IFERROR(INDEX('👾 RAW MAPPING'!$B$59:$B$73, SMALL(IF('👾 RAW MAPPING'!$B$59:$B$73<>"", ROW('👾 RAW MAPPING'!$B$59:$B$73)-ROW('👾 RAW MAPPING'!$B$59)+1), ROW(B4)-ROW(B$2)+1)), "")} | C4: {=IFERROR(INDEX('👾 RAW MAPPING'!$C$59:$C$73, SMALL(IF('👾 RAW MAPPING'!$C$59:$C$73<>"", ROW('👾 RAW MAPPING'!$C$59:$C$73)-ROW('👾 RAW MAPPING'!$C$59)+1), ROW(C4)-ROW(C$2)+1)), "")} | F4: {=IFERROR(INDEX('👾 RAW MAPPING'!$F$59:$F$73, SMALL(IF('👾 RAW MAPPING'!$F$59:$F$73<>"", ROW('👾 RAW MAPPING'!$F$59:$F$73)-ROW('👾 RAW MAPPING'!$F$59)+1), ROW(F4)-ROW(F$2)+1)), "")} | G4: {=IFERROR(INDEX('👾 RAW MAPPING'!$G$59:$G$73, SMALL(IF('👾 RAW MAPPING'!$G$59:$G$73<>"", ROW('👾 RAW MAPPING'!$G$59:$G$73)-ROW('👾 RAW MAPPING'!$G$59)+1), ROW(G4)-ROW(G$2)+1)), "")} | M4: {=IFERROR(INDEX('👾 RAW MAPPING'!$M$59:$M$73, SMALL(IF('👾 RAW MAPPING'!$M$59:$M$73<>"", ROW('👾 RAW MAPPING'!$M$59:$M$73)-ROW('👾 RAW MAPPING'!$M$59)+1), ROW(M4)-ROW(M$2)+1)), "")} | N4: =IF(A4<>"",TODAY(),"") | S4: =IF(A4<>"","yes","") | U4: =IF(A4<>"",TODAY(),"")
A5: {=IFERROR(INDEX('👾 RAW MAPPING'!$A$59:$A$73, SMALL(IF('👾 RAW MAPPING'!$A$59:$A$73<>"", ROW('👾 RAW MAPPING'!$A$59:$A$73)-ROW('👾 RAW MAPPING'!$A$59)+1), ROW(A5)-ROW(A$2)+1)), "")} | B5: {=IFERROR(INDEX('👾 RAW MAPPING'!$B$59:$B$73, SMALL(IF('👾 RAW MAPPING'!$B$59:$B$73<>"", ROW('👾 RAW MAPPING'!$B$59:$B$73)-ROW('👾 RAW MAPPING'!$B$59)+1), ROW(B5)-ROW(B$2)+1)), "")} | C5: {=IFERROR(INDEX('👾 RAW MAPPING'!$C$59:$C$73, SMALL(IF('👾 RAW MAPPING'!$C$59:$C$73<>"", ROW('👾 RAW MAPPING'!$C$59:$C$73)-ROW('👾 RAW MAPPING'!$C$59)+1), ROW(C5)-ROW(C$2)+1)), "")} | F5: {=IFERROR(INDEX('👾 RAW MAPPING'!$F$59:$F$73, SMALL(IF('👾 RAW MAPPING'!$F$59:$F$73<>"", ROW('👾 RAW MAPPING'!$F$59:$F$73)-ROW('👾 RAW MAPPING'!$F$59)+1), ROW(F5)-ROW(F$2)+1)), "")} | G5: {=IFERROR(INDEX('👾 RAW MAPPING'!$G$59:$G$73, SMALL(IF('👾 RAW MAPPING'!$G$59:$G$73<>"", ROW('👾 RAW MAPPING'!$G$59:$G$73)-ROW('👾 RAW MAPPING'!$G$59)+1), ROW(G5)-ROW(G$2)+1)), "")} | M5: {=IFERROR(INDEX('👾 RAW MAPPING'!$M$59:$M$73, SMALL(IF('👾 RAW MAPPING'!$M$59:$M$73<>"", ROW('👾 RAW MAPPING'!$M$59:$M$73)-ROW('👾 RAW MAPPING'!$M$59)+1), ROW(M5)-ROW(M$2)+1)), "")} | N5: =IF(A5<>"",TODAY(),"") | S5: =IF(A5<>"","yes","") | U5: =IF(A5<>"",TODAY(),"")
A6: {=IFERROR(INDEX('👾 RAW MAPPING'!$A$59:$A$73, SMALL(IF('👾 RAW MAPPING'!$A$59:$A$73<>"", ROW('👾 RAW MAPPING'!$A$59:$A$73)-ROW('👾 RAW MAPPING'!$A$59)+1), ROW(A6)-ROW(A$2)+1)), "")} | B6: {=IFERROR(INDEX('👾 RAW MAPPING'!$B$59:$B$73, SMALL(IF('👾 RAW MAPPING'!$B$59:$B$73<>"", ROW('👾 RAW MAPPING'!$B$59:$B$73)-ROW('👾 RAW MAPPING'!$B$59)+1), ROW(B6)-ROW(B$2)+1)), "")} | C6: {=IFERROR(INDEX('👾 RAW MAPPING'!$C$59:$C$73, SMALL(IF('👾 RAW MAPPING'!$C$59:$C$73<>"", ROW('👾 RAW MAPPING'!$C$59:$C$73)-ROW('👾 RAW MAPPING'!$C$59)+1), ROW(C6)-ROW(C$2)+1)), "")} | F6: {=IFERROR(INDEX('👾 RAW MAPPING'!$F$59:$F$73, SMALL(IF('👾 RAW MAPPING'!$F$59:$F$73<>"", ROW('👾 RAW MAPPING'!$F$59:$F$73)-ROW('👾 RAW MAPPING'!$F$59)+1), ROW(F6)-ROW(F$2)+1)), "")} | G6: {=IFERROR(INDEX('👾 RAW MAPPING'!$G$59:$G$73, SMALL(IF('👾 RAW MAPPING'!$G$59:$G$73<>"", ROW('👾 RAW MAPPING'!$G$59:$G$73)-ROW('👾 RAW MAPPING'!$G$59)+1), ROW(G6)-ROW(G$2)+1)), "")} | M6: {=IFERROR(INDEX('👾 RAW MAPPING'!$M$59:$M$73, SMALL(IF('👾 RAW MAPPING'!$M$59:$M$73<>"", ROW('👾 RAW MAPPING'!$M$59:$M$73)-ROW('👾 RAW MAPPING'!$M$59)+1), ROW(M6)-ROW(M$2)+1)), "")} | N6: =IF(A6<>"",TODAY(),"") | S6: =IF(A6<>"","yes","") | U6: =IF(A6<>"",TODAY(),"")
A7: {=IFERROR(INDEX('👾 RAW MAPPING'!$A$59:$A$73, SMALL(IF('👾 RAW MAPPING'!$A$59:$A$73<>"", ROW('👾 RAW MAPPING'!$A$59:$A$73)-ROW('👾 RAW MAPPING'!$A$59)+1), ROW(A7)-ROW(A$2)+1)), "")} | B7: {=IFERROR(INDEX('👾 RAW MAPPING'!$B$59:$B$73, SMALL(IF('👾 RAW MAPPING'!$B$59:$B$73<>"", ROW('👾 RAW MAPPING'!$B$59:$B$73)-ROW('👾 RAW MAPPING'!$B$59)+1), ROW(B7)-ROW(B$2)+1)), "")} | C7: {=IFERROR(INDEX('👾 RAW MAPPING'!$C$59:$C$73, SMALL(IF('👾 RAW MAPPING'!$C$59:$C$73<>"", ROW('👾 RAW MAPPING'!$C$59:$C$73)-ROW('👾 RAW MAPPING'!$C$59)+1), ROW(C7)-ROW(C$2)+1)), "")} | F7: {=IFERROR(INDEX('👾 RAW MAPPING'!$F$59:$F$73, SMALL(IF('👾 RAW MAPPING'!$F$59:$F$73<>"", ROW('👾 RAW MAPPING'!$F$59:$F$73)-ROW('👾 RAW MAPPING'!$F$59)+1), ROW(F7)-ROW(F$2)+1)), "")} | G7: {=IFERROR(INDEX('👾 RAW MAPPING'!$G$59:$G$73, SMALL(IF('👾 RAW MAPPING'!$G$59:$G$73<>"", ROW('👾 RAW MAPPING'!$G$59:$G$73)-ROW('👾 RAW MAPPING'!$G$59)+1), ROW(G7)-ROW(G$2)+1)), "")} | M7: {=IFERROR(INDEX('👾 RAW MAPPING'!$M$59:$M$73, SMALL(IF('👾 RAW MAPPING'!$M$59:$M$73<>"", ROW('👾 RAW MAPPING'!$M$59:$M$73)-ROW('👾 RAW MAPPING'!$M$59)+1), ROW(M7)-ROW(M$2)+1)), "")} | N7: =IF(A7<>"",TODAY(),"") | S7: =IF(A7<>"","yes","") | U7: =IF(A7<>"",TODAY(),"")
A8: {=IFERROR(INDEX('👾 RAW MAPPING'!$A$59:$A$73, SMALL(IF('👾 RAW MAPPING'!$A$59:$A$73<>"", ROW('👾 RAW MAPPING'!$A$59:$A$73)-ROW('👾 RAW MAPPING'!$A$59)+1), ROW(A8)-ROW(A$2)+1)), "")} | B8: {=IFERROR(INDEX('👾 RAW MAPPING'!$B$59:$B$73, SMALL(IF('👾 RAW MAPPING'!$B$59:$B$73<>"", ROW('👾 RAW MAPPING'!$B$59:$B$73)-ROW('👾 RAW MAPPING'!$B$59)+1), ROW(B8)-ROW(B$2)+1)), "")} | C8: {=IFERROR(INDEX('👾 RAW MAPPING'!$C$59:$C$73, SMALL(IF('👾 RAW MAPPING'!$C$59:$C$73<>"", ROW('👾 RAW MAPPING'!$C$59:$C$73)-ROW('👾 RAW MAPPING'!$C$59)+1), ROW(C8)-ROW(C$2)+1)), "")} | F8: {=IFERROR(INDEX('👾 RAW MAPPING'!$F$59:$F$73, SMALL(IF('👾 RAW MAPPING'!$F$59:$F$73<>"", ROW('👾 RAW MAPPING'!$F$59:$F$73)-ROW('👾 RAW MAPPING'!$F$59)+1), ROW(F8)-ROW(F$2)+1)), "")} | G8: {=IFERROR(INDEX('👾 RAW MAPPING'!$G$59:$G$73, SMALL(IF('👾 RAW MAPPING'!$G$59:$G$73<>"", ROW('👾 RAW MAPPING'!$G$59:$G$73)-ROW('👾 RAW MAPPING'!$G$59)+1), ROW(G8)-ROW(G$2)+1)), "")} | M8: {=IFERROR(INDEX('👾 RAW MAPPING'!$M$59:$M$73, SMALL(IF('👾 RAW MAPPING'!$M$59:$M$73<>"", ROW('👾 RAW MAPPING'!$M$59:$M$73)-ROW('👾 RAW MAPPING'!$M$59)+1), ROW(M8)-ROW(M$2)+1)), "")} | N8: =IF(A8<>"",TODAY(),"") | S8: =IF(A8<>"","yes","") | U8: =IF(A8<>"",TODAY(),"")
A9: {=IFERROR(INDEX('👾 RAW MAPPING'!$A$59:$A$73, SMALL(IF('👾 RAW MAPPING'!$A$59:$A$73<>"", ROW('👾 RAW MAPPING'!$A$59:$A$73)-ROW('👾 RAW MAPPING'!$A$59)+1), ROW(A9)-ROW(A$2)+1)), "")} | B9: {=IFERROR(INDEX('👾 RAW MAPPING'!$B$59:$B$73, SMALL(IF('👾 RAW MAPPING'!$B$59:$B$73<>"", ROW('👾 RAW MAPPING'!$B$59:$B$73)-ROW('👾 RAW MAPPING'!$B$59)+1), ROW(B9)-ROW(B$2)+1)), "")} | C9: {=IFERROR(INDEX('👾 RAW MAPPING'!$C$59:$C$73, SMALL(IF('👾 RAW MAPPING'!$C$59:$C$73<>"", ROW('👾 RAW MAPPING'!$C$59:$C$73)-ROW('👾 RAW MAPPING'!$C$59)+1), ROW(C9)-ROW(C$2)+1)), "")} | F9: {=IFERROR(INDEX('👾 RAW MAPPING'!$F$59:$F$73, SMALL(IF('👾 RAW MAPPING'!$F$59:$F$73<>"", ROW('👾 RAW MAPPING'!$F$59:$F$73)-ROW('👾 RAW MAPPING'!$F$59)+1), ROW(F9)-ROW(F$2)+1)), "")} | G9: {=IFERROR(INDEX('👾 RAW MAPPING'!$G$59:$G$73, SMALL(IF('👾 RAW MAPPING'!$G$59:$G$73<>"", ROW('👾 RAW MAPPING'!$G$59:$G$73)-ROW('👾 RAW MAPPING'!$G$59)+1), ROW(G9)-ROW(G$2)+1)), "")} | M9: {=IFERROR(INDEX('👾 RAW MAPPING'!$M$59:$M$73, SMALL(IF('👾 RAW MAPPING'!$M$59:$M$73<>"", ROW('👾 RAW MAPPING'!$M$59:$M$73)-ROW('👾 RAW MAPPING'!$M$59)+1), ROW(M9)-ROW(M$2)+1)), "")} | N9: =IF(A9<>"",TODAY(),"") | S9: =IF(A9<>"","yes","") | U9: =IF(A9<>"",TODAY(),"")
A10: {=IFERROR(INDEX('👾 RAW MAPPING'!$A$59:$A$73, SMALL(IF('👾 RAW MAPPING'!$A$59:$A$73<>"", ROW('👾 RAW MAPPING'!$A$59:$A$73)-ROW('👾 RAW MAPPING'!$A$59)+1), ROW(A10)-ROW(A$2)+1)), "")} | B10: {=IFERROR(INDEX('👾 RAW MAPPING'!$B$59:$B$73, SMALL(IF('👾 RAW MAPPING'!$B$59:$B$73<>"", ROW('👾 RAW MAPPING'!$B$59:$B$73)-ROW('👾 RAW MAPPING'!$B$59)+1), ROW(B10)-ROW(B$2)+1)), "")} | C10: {=IFERROR(INDEX('👾 RAW MAPPING'!$C$59:$C$73, SMALL(IF('👾 RAW MAPPING'!$C$59:$C$73<>"", ROW('👾 RAW MAPPING'!$C$59:$C$73)-ROW('👾 RAW MAPPING'!$C$59)+1), ROW(C10)-ROW(C$2)+1)), "")} | F10: {=IFERROR(INDEX('👾 RAW MAPPING'!$F$59:$F$73, SMALL(IF('👾 RAW MAPPING'!$F$59:$F$73<>"", ROW('👾 RAW MAPPING'!$F$59:$F$73)-ROW('👾 RAW MAPPING'!$F$59)+1), ROW(F10)-ROW(F$2)+1)), "")} | G10: {=IFERROR(INDEX('👾 RAW MAPPING'!$G$59:$G$73, SMALL(IF('👾 RAW MAPPING'!$G$59:$G$73<>"", ROW('👾 RAW MAPPING'!$G$59:$G$73)-ROW('👾 RAW MAPPING'!$G$59)+1), ROW(G10)-ROW(G$2)+1)), "")} | M10: {=IFERROR(INDEX('👾 RAW MAPPING'!$M$59:$M$73, SMALL(IF('👾 RAW MAPPING'!$M$59:$M$73<>"", ROW('👾 RAW MAPPING'!$M$59:$M$73)-ROW('👾 RAW MAPPING'!$M$59)+1), ROW(M10)-ROW(M$2)+1)), "")} | N10: =IF(A10<>"",TODAY(),"") | S10: =IF(A10<>"","yes","") | U10: =IF(A10<>"",TODAY(),"")
A11: {=IFERROR(INDEX('👾 RAW MAPPING'!$A$59:$A$73, SMALL(IF('👾 RAW MAPPING'!$A$59:$A$73<>"", ROW('👾 RAW MAPPING'!$A$59:$A$73)-ROW('👾 RAW MAPPING'!$A$59)+1), ROW(A11)-ROW(A$2)+1)), "")} | B11: {=IFERROR(INDEX('👾 RAW MAPPING'!$B$59:$B$73, SMALL(IF('👾 RAW MAPPING'!$B$59:$B$73<>"", ROW('👾 RAW MAPPING'!$B$59:$B$73)-ROW('👾 RAW MAPPING'!$B$59)+1), ROW(B11)-ROW(B$2)+1)), "")} | C11: {=IFERROR(INDEX('👾 RAW MAPPING'!$C$59:$C$73, SMALL(IF('👾 RAW MAPPING'!$C$59:$C$73<>"", ROW('👾 RAW MAPPING'!$C$59:$C$73)-ROW('👾 RAW MAPPING'!$C$59)+1), ROW(C11)-ROW(C$2)+1)), "")} | F11: {=IFERROR(INDEX('👾 RAW MAPPING'!$F$59:$F$73, SMALL(IF('👾 RAW MAPPING'!$F$59:$F$73<>"", ROW('👾 RAW MAPPING'!$F$59:$F$73)-ROW('👾 RAW MAPPING'!$F$59)+1), ROW(F11)-ROW(F$2)+1)), "")} | G11: {=IFERROR(INDEX('👾 RAW MAPPING'!$G$59:$G$73, SMALL(IF('👾 RAW MAPPING'!$G$59:$G$73<>"", ROW('👾 RAW MAPPING'!$G$59:$G$73)-ROW('👾 RAW MAPPING'!$G$59)+1), ROW(G11)-ROW(G$2)+1)), "")} | M11: {=IFERROR(INDEX('👾 RAW MAPPING'!$M$59:$M$73, SMALL(IF('👾 RAW MAPPING'!$M$59:$M$73<>"", ROW('👾 RAW MAPPING'!$M$59:$M$73)-ROW('👾 RAW MAPPING'!$M$59)+1), ROW(M11)-ROW(M$2)+1)), "")} | N11: =IF(A11<>"",TODAY(),"") | S11: =IF(A11<>"","yes","") | U11: =IF(A11<>"",TODAY(),"")
A12: {=IFERROR(INDEX('👾 RAW MAPPING'!$A$59:$A$73, SMALL(IF('👾 RAW MAPPING'!$A$59:$A$73<>"", ROW('👾 RAW MAPPING'!$A$59:$A$73)-ROW('👾 RAW MAPPING'!$A$59)+1), ROW(A12)-ROW(A$2)+1)), "")} | B12: {=IFERROR(INDEX('👾 RAW MAPPING'!$B$59:$B$73, SMALL(IF('👾 RAW MAPPING'!$B$59:$B$73<>"", ROW('👾 RAW MAPPING'!$B$59:$B$73)-ROW('👾 RAW MAPPING'!$B$59)+1), ROW(B12)-ROW(B$2)+1)), "")} | C12: {=IFERROR(INDEX('👾 RAW MAPPING'!$C$59:$C$73, SMALL(IF('👾 RAW MAPPING'!$C$59:$C$73<>"", ROW('👾 RAW MAPPING'!$C$59:$C$73)-ROW('👾 RAW MAPPING'!$C$59)+1), ROW(C12)-ROW(C$2)+1)), "")} | F12: {=IFERROR(INDEX('👾 RAW MAPPING'!$F$59:$F$73, SMALL(IF('👾 RAW MAPPING'!$F$59:$F$73<>"", ROW('👾 RAW MAPPING'!$F$59:$F$73)-ROW('👾 RAW MAPPING'!$F$59)+1), ROW(F12)-ROW(F$2)+1)), "")} | G12: {=IFERROR(INDEX('👾 RAW MAPPING'!$G$59:$G$73, SMALL(IF('👾 RAW MAPPING'!$G$59:$G$73<>"", ROW('👾 RAW MAPPING'!$G$59:$G$73)-ROW('👾 RAW MAPPING'!$G$59)+1), ROW(G12)-ROW(G$2)+1)), "")} | M12: {=IFERROR(INDEX('👾 RAW MAPPING'!$M$59:$M$73, SMALL(IF('👾 RAW MAPPING'!$M$59:$M$73<>"", ROW('👾 RAW MAPPING'!$M$59:$M$73)-ROW('👾 RAW MAPPING'!$M$59)+1), ROW(M12)-ROW(M$2)+1)), "")} | N12: =IF(A12<>"",TODAY(),"") | S12: =IF(A12<>"","yes","") | U12: =IF(A12<>"",TODAY(),"")
A13: {=IFERROR(INDEX('👾 RAW MAPPING'!$A$59:$A$73, SMALL(IF('👾 RAW MAPPING'!$A$59:$A$73<>"", ROW('👾 RAW MAPPING'!$A$59:$A$73)-ROW('👾 RAW MAPPING'!$A$59)+1), ROW(A13)-ROW(A$2)+1)), "")} | B13: {=IFERROR(INDEX('👾 RAW MAPPING'!$B$59:$B$73, SMALL(IF('👾 RAW MAPPING'!$B$59:$B$73<>"", ROW('👾 RAW MAPPING'!$B$59:$B$73)-ROW('👾 RAW MAPPING'!$B$59)+1), ROW(B13)-ROW(B$2)+1)), "")} | C13: {=IFERROR(INDEX('👾 RAW MAPPING'!$C$59:$C$73, SMALL(IF('👾 RAW MAPPING'!$C$59:$C$73<>"", ROW('👾 RAW MAPPING'!$C$59:$C$73)-ROW('👾 RAW MAPPING'!$C$59)+1), ROW(C13)-ROW(C$2)+1)), "")} | F13: {=IFERROR(INDEX('👾 RAW MAPPING'!$F$59:$F$73, SMALL(IF('👾 RAW MAPPING'!$F$59:$F$73<>"", ROW('👾 RAW MAPPING'!$F$59:$F$73)-ROW('👾 RAW MAPPING'!$F$59)+1), ROW(F13)-ROW(F$2)+1)), "")} | G13: {=IFERROR(INDEX('👾 RAW MAPPING'!$G$59:$G$73, SMALL(IF('👾 RAW MAPPING'!$G$59:$G$73<>"", ROW('👾 RAW MAPPING'!$G$59:$G$73)-ROW('👾 RAW MAPPING'!$G$59)+1), ROW(G13)-ROW(G$2)+1)), "")} | M13: {=IFERROR(INDEX('👾 RAW MAPPING'!$M$59:$M$73, SMALL(IF('👾 RAW MAPPING'!$M$59:$M$73<>"", ROW('👾 RAW MAPPING'!$M$59:$M$73)-ROW('👾 RAW MAPPING'!$M$59)+1), ROW(M13)-ROW(M$2)+1)), "")} | N13: =IF(A13<>"",TODAY(),"") | S13: =IF(A13<>"","yes","") | U13: =IF(A13<>"",TODAY(),"")
... A16: {=IFERROR(INDEX('👾 RAW MAPPING'!$A$59:$A$73, SMALL(IF('👾 RAW MAPPING'!$A$59:$A$73<>"", ROW('👾 RAW MAPPING'!$A$59:$A$73)-ROW('👾 RAW MAPPING'!$A$59)+1), ROW(A16)-ROW(A$2)+1)), "")} | B16: {=IFERROR(INDEX('👾 RAW MAPPING'!$B$59:$B$73, SMALL(IF('👾 RAW MAPPING'!$B$59:$B$73<>"", ROW('👾 RAW MAPPING'!$B$59:$B$73)-ROW('👾 RAW MAPPING'!$B$59)+1), ROW(B16)-ROW(B$2)+1)), "")} | C16: {=IFERROR(INDEX('👾 RAW MAPPING'!$C$59:$C$73, SMALL(IF('👾 RAW MAPPING'!$C$59:$C$73<>"", ROW('👾 RAW MAPPING'!$C$59:$C$73)-ROW('👾 RAW MAPPING'!$C$59)+1), ROW(C16)-ROW(C$2)+1)), "")} | F16: {=IFERROR(INDEX('👾 RAW MAPPING'!$F$59:$F$73, SMALL(IF('👾 RAW MAPPING'!$F$59:$F$73<>"", ROW('👾 RAW MAPPING'!$F$59:$F$73)-ROW('👾 RAW MAPPING'!$F$59)+1), ROW(F16)-ROW(F$2)+1)), "")} | G16: {=IFERROR(INDEX('👾 RAW MAPPING'!$G$59:$G$73, SMALL(IF('👾 RAW MAPPING'!$G$59:$G$73<>"", ROW('👾 RAW MAPPING'!$G$59:$G$73)-ROW('👾 RAW MAPPING'!$G$59)+1), ROW(G16)-ROW(G$2)+1)), "")} | M16: {=IFERROR(INDEX('👾 RAW MAPPING'!$M$59:$M$73, SMALL(IF('👾 RAW MAPPING'!$M$59:$M$73<>"", ROW('👾 RAW MAPPING'!$M$59:$M$73)-ROW('👾 RAW MAPPING'!$M$59)+1), ROW(M16)-ROW(M$2)+1)), "")} | N16: =IF(A16<>"",TODAY(),"") | S16: =IF(A16<>"","yes","") | U16: =IF(A16<>"",TODAY(),"")

Sheet 💰 Prepayment notice
B3: Skipr SA/NV
B5: Cantersteen 12
B6: 1000 Brussels
B7: BE0712537551
C8: ACCENTURE OPERATIONS CLIENT SERVICES SA
B10: Prepayment notice | F10: =VLOOKUP(C8,'🤝 Client information'!C80:K89 , 6, FALSE) -> #N/A
F11: =VLOOKUP(C8,'🤝 Client information'!C80:K89 , 9, FALSE) -> #N/A
F12: =VLOOKUP(C8,'🤝 Client information'!C80:K89 , 5, FALSE) -> #N/A
B15: date
B16: =today() -> 46155 | D16: - | E16: -
B18: Description | F18: Amount
B19: Prepayment Mobility Budget | F19: 1
B25: Total hors TVA | F25: =F19 -> 1
B26: TVA | F26: n/a
B27: A payer, TVAc | F27: =F25 -> 1
B31: Your payment account: | F31: =VLOOKUP(C8,'👾 RAW MAPPING'!F6:J15 , 5, FALSE) -> #N/A
B32: BIC: | F32: TRZOFR21

Sheet 👾 RAW MAPPING
A2: 👾 | B2: Raw mapping
A5: Skipr team contacts (sheet client information 3.4) | F5: Entity name | J5: IBAN wallet
A6: Hélène | B6: Marcq | C6: helene@skipr.co | D6: +32499349511 | F6: ='🤝 Client information'!C80 | K6: < To be completed by CSM
A7: Maroussia | B7: Collette | C7: maroussia@skipr.co | D7: +32479433369 | F7: ='🤝 Client information'!C81
A8: Steve | B8: Boutremans | C8: steve.boutremans@skipr.co | F8: ='🤝 Client information'!C82
A9: Maxim | B9: Snyers | C9: maxim@skipr.co | D9: +32474573339 | F9: ='🤝 Client information'!C83
A10: Charlie | B10: Millgate | C10: charlie@skipr.co | D10: +32492729294 | F10: ='🤝 Client information'!C84
A11: Denis | B11: Huberland | C11: denis@skipr.co | D11: +32484555086 | F11: ='🤝 Client information'!C85
A12: Victor | B12: Rembours | C12: victor@skipr.co | D12: +33659612262 | F12: ='🤝 Client information'!C86
A13: Jerome | B13: Dambrain | C13: jerome@skipr.co | D13: +32499640271 | F13: ='🤝 Client information'!C87
A14: Thaïs | B14: Launay | C14: Thais@skipr.co | D14: +33603244564 | F14: ='🤝 Client information'!C88
F15: ='🤝 Client information'!C89
A17: Sum-up of services per program without blanks in between (used in sheet Validation briefing)
A18: Program 1 | B18: Services | C18: Program 2 | D18: Services | E18: Program 3 | F18: Services | G18: Program 4 | H18: Services | I18: Program 5 | J18: Services
A19: =IF('🚀 Mobility program(s)'!M42="yes",'🚀 Mobility program(s)'!E42,"") | C19: =IF('🚀 Mobility program(s)'!M136="yes",'🚀 Mobility program(s)'!E136,"") | E19: =IF('🚀 Mobility program(s)'!M230="yes",'🚀 Mobility program(s)'!E230,"") | G19: =IF('🚀 Mobility program(s)'!M324="yes",'🚀 Mobility program(s)'!E324,"") | I19: =IF('🚀 Mobility program(s)'!M418="yes",'🚀 Mobility program(s)'!E418,"")
A20: =IF('🚀 Mobility program(s)'!M43="yes",'🚀 Mobility program(s)'!E43,"") | C20: =IF('🚀 Mobility program(s)'!M137="yes",'🚀 Mobility program(s)'!E137,"") | E20: =IF('🚀 Mobility program(s)'!M231="yes",'🚀 Mobility program(s)'!E231,"") | G20: =IF('🚀 Mobility program(s)'!M325="yes",'🚀 Mobility program(s)'!E325,"") | I20: =IF('🚀 Mobility program(s)'!M419="yes",'🚀 Mobility program(s)'!E419,"")
A21: =IF('🚀 Mobility program(s)'!M44="yes",'🚀 Mobility program(s)'!E44,"") | C21: =IF('🚀 Mobility program(s)'!M138="yes",'🚀 Mobility program(s)'!E138,"") | E21: =IF('🚀 Mobility program(s)'!M232="yes",'🚀 Mobility program(s)'!E232,"") | G21: =IF('🚀 Mobility program(s)'!M326="yes",'🚀 Mobility program(s)'!E326,"") | I21: =IF('🚀 Mobility program(s)'!M420="yes",'🚀 Mobility program(s)'!E420,"")
A22: =IF('🚀 Mobility program(s)'!M45="yes",'🚀 Mobility program(s)'!E45,"") | C22: =IF('🚀 Mobility program(s)'!M139="yes",'🚀 Mobility program(s)'!E139,"") | E22: =IF('🚀 Mobility program(s)'!M233="yes",'🚀 Mobility program(s)'!E233,"") | G22: =IF('🚀 Mobility program(s)'!M327="yes",'🚀 Mobility program(s)'!E327,"") | I22: =IF('🚀 Mobility program(s)'!M421="yes",'🚀 Mobility program(s)'!E421,"")
A23: =IF('🚀 Mobility program(s)'!M46="yes",'🚀 Mobility program(s)'!E46,"") | C23: =IF('🚀 Mobility program(s)'!M140="yes",'🚀 Mobility program(s)'!E140,"") | E23: =IF('🚀 Mobility program(s)'!M234="yes",'🚀 Mobility program(s)'!E234,"") | G23: =IF('🚀 Mobility program(s)'!M328="yes",'🚀 Mobility program(s)'!E328,"") | I23: =IF('🚀 Mobility program(s)'!M422="yes",'🚀 Mobility program(s)'!E422,"")
A24: =IF('🚀 Mobility program(s)'!M47="yes",'🚀 Mobility program(s)'!E47,"") | C24: =IF('🚀 Mobility program(s)'!M141="yes",'🚀 Mobility program(s)'!E141,"") | E24: =IF('🚀 Mobility program(s)'!M235="yes",'🚀 Mobility program(s)'!E235,"") | G24: =IF('🚀 Mobility program(s)'!M329="yes",'🚀 Mobility program(s)'!E329,"") | I24: =IF('🚀 Mobility program(s)'!M423="yes",'🚀 Mobility program(s)'!E423,"")
A25: =IF('🚀 Mobility program(s)'!M48="yes",'🚀 Mobility program(s)'!E48,"") | C25: =IF('🚀 Mobility program(s)'!M142="yes",'🚀 Mobility program(s)'!E142,"") | E25: =IF('🚀 Mobility program(s)'!M236="yes",'🚀 Mobility program(s)'!E236,"") | G25: =IF('🚀 Mobility program(s)'!M330="yes",'🚀 Mobility program(s)'!E330,"") | I25: =IF('🚀 Mobility program(s)'!M424="yes",'🚀 Mobility program(s)'!E424,"")
A26: =IF('🚀 Mobility program(s)'!M49="yes",'🚀 Mobility program(s)'!E49,"") | C26: =IF('🚀 Mobility program(s)'!M143="yes",'🚀 Mobility program(s)'!E143,"") | E26: =IF('🚀 Mobility program(s)'!M237="yes",'🚀 Mobility program(s)'!E237,"") | G26: =IF('🚀 Mobility program(s)'!M331="yes",'🚀 Mobility program(s)'!E331,"") | I26: =IF('🚀 Mobility program(s)'!M425="yes",'🚀 Mobility program(s)'!E425,"")
A27: =IF('🚀 Mobility program(s)'!M50="yes",'🚀 Mobility program(s)'!E50,"") | C27: =IF('🚀 Mobility program(s)'!M144="yes",'🚀 Mobility program(s)'!E144,"") | E27: =IF('🚀 Mobility program(s)'!M238="yes",'🚀 Mobility program(s)'!E238,"") | G27: =IF('🚀 Mobility program(s)'!M332="yes",'🚀 Mobility program(s)'!E332,"") | I27: =IF('🚀 Mobility program(s)'!M426="yes",'🚀 Mobility program(s)'!E426,"")
A28: =IF('🚀 Mobility program(s)'!M51="yes",'🚀 Mobility program(s)'!E51,"") | C28: =IF('🚀 Mobility program(s)'!M145="yes",'🚀 Mobility program(s)'!E145,"") | E28: =IF('🚀 Mobility program(s)'!M239="yes",'🚀 Mobility program(s)'!E239,"") | G28: =IF('🚀 Mobility program(s)'!M333="yes",'🚀 Mobility program(s)'!E333,"") | I28: =IF('🚀 Mobility program(s)'!M427="yes",'🚀 Mobility program(s)'!E427,"")
A29: =IF('🚀 Mobility program(s)'!M52="yes",'🚀 Mobility program(s)'!E52,"") | C29: =IF('🚀 Mobility program(s)'!M146="yes",'🚀 Mobility program(s)'!E146,"") | E29: =IF('🚀 Mobility program(s)'!M240="yes",'🚀 Mobility program(s)'!E240,"") | G29: =IF('🚀 Mobility program(s)'!M334="yes",'🚀 Mobility program(s)'!E334,"") | I29: =IF('🚀 Mobility program(s)'!M428="yes",'🚀 Mobility program(s)'!E428,"")
A30: =IF('🚀 Mobility program(s)'!M53="yes",'🚀 Mobility program(s)'!E53,"") | C30: =IF('🚀 Mobility program(s)'!M147="yes",'🚀 Mobility program(s)'!E147,"") | E30: =IF('🚀 Mobility program(s)'!M241="yes",'🚀 Mobility program(s)'!E241,"") | G30: =IF('🚀 Mobility program(s)'!M335="yes",'🚀 Mobility program(s)'!E335,"") | I30: =IF('🚀 Mobility program(s)'!M429="yes",'🚀 Mobility program(s)'!E429,"")
... A55: =IF('🚀 Mobility program(s)'!M78="yes",'🚀 Mobility program(s)'!E78,"") | C55: =IF('🚀 Mobility program(s)'!M172="yes",'🚀 Mobility program(s)'!E172,"") | E55: =IF('🚀 Mobility program(s)'!M266="yes",'🚀 Mobility program(s)'!E266,"") | G55: =IF('🚀 Mobility program(s)'!M360="yes",'🚀 Mobility program(s)'!E360,"") | I55: =IF('🚀 Mobility program(s)'!M454="yes",'🚀 Mobility program(s)'!E454,"")
A57: Admin creation file sheet (used to exclude blank hereunder, but also to exclude admins with only access to some entities (see sheet Client Information) and and the ones that are checked as created (see sheet client information)
A58: first_name | B58: last_name | C58: email | D58: phone_number | E58: phone_number_country_code | F58: language | G58: gender | H58: date_of_birth | I58: place_of_birth | J58: country_of_birth | K58: nationality | L58: job_title | M58: role | N58: start_on | O58: address__street | P58: address__postal_code | Q58: address__city | R58: address__country_code | S58: new_gen | T58: group_name | U58: invite_on | V58: use_physical_card | W58: internal_payroll_id | X58: cost_center
A59: =IF('🤝 Client information'!Q112,"",IF('🤝 Client information'!K112="yes",'🤝 Client information'!C112,"")) | B59: =IF('🤝 Client information'!Q112,"",IF('🤝 Client information'!K112="yes",'🤝 Client information'!D112,"")) | C59: =IF('🤝 Client information'!Q112,"",IF('🤝 Client information'!K112="yes",'🤝 Client information'!F112,"")) | F59: =IF('🤝 Client information'!Q112,"",IF('🤝 Client information'!K112="yes",'🤝 Client information'!I112,"")) | G59: =IF('🤝 Client information'!Q112,"",IF('🤝 Client information'!K112="yes",'🤝 Client information'!J112,"")) | M59: =IF('🤝 Client information'!Q112, "", IF(AND('🤝 Client information'!K112="yes", '🤝 Client information'!N112="yes"), "EMPLOYEE", IF(AND('🤝 Client information'!K112="yes", '🤝 Client information'!N112="no", '🤝 Client information'!H112="Finance & Accounting"), "CONTROLLER", IF(AND('🤝 Client information'!K112="yes", '🤝 Client information'!N112="no", '🤝 Client information'!H112<>"Finance & Accounting"), "FLEET_MGR", "")))) | N59: =IF(A59<>"",TODAY(),"") | S59: =IF(A59<>"","yes","") | U59: =IF(A59<>"",TODAY(),"")
A60: =IF('🤝 Client information'!Q113,"",IF('🤝 Client information'!K113="yes",'🤝 Client information'!C113,"")) | B60: =IF('🤝 Client information'!Q113,"",IF('🤝 Client information'!K113="yes",'🤝 Client information'!D113,"")) | C60: =IF('🤝 Client information'!Q113,"",IF('🤝 Client information'!K113="yes",'🤝 Client information'!F113,"")) | F60: =IF('🤝 Client information'!Q113,"",IF('🤝 Client information'!K113="yes",'🤝 Client information'!I113,"")) | G60: =IF('🤝 Client information'!Q113,"",IF('🤝 Client information'!K113="yes",'🤝 Client information'!J113,"")) | M60: =IF('🤝 Client information'!Q113, "", IF(AND('🤝 Client information'!K113="yes", '🤝 Client information'!N113="yes"), "EMPLOYEE", IF(AND('🤝 Client information'!K113="yes", '🤝 Client information'!N113="no", '🤝 Client information'!H113="Finance & Accounting"), "CONTROLLER", IF(AND('🤝 Client information'!K113="yes", '🤝 Client information'!N113="no", '🤝 Client information'!H113<>"Finance & Accounting"), "FLEET_MGR", "")))) | N60: =IF(A60<>"",TODAY(),"") | S60: =IF(A60<>"","yes","") | U60: =IF(A60<>"",TODAY(),"")
A61: =IF('🤝 Client information'!Q114,"",IF('🤝 Client information'!K114="yes",'🤝 Client information'!C114,"")) | B61: =IF('🤝 Client information'!Q114,"",IF('🤝 Client information'!K114="yes",'🤝 Client information'!D114,"")) | C61: =IF('🤝 Client information'!Q114,"",IF('🤝 Client information'!K114="yes",'🤝 Client information'!F114,"")) | F61: =IF('🤝 Client information'!Q114,"",IF('🤝 Client information'!K114="yes",'🤝 Client information'!I114,"")) | G61: =IF('🤝 Client information'!Q114,"",IF('🤝 Client information'!K114="yes",'🤝 Client information'!J114,"")) | M61: =IF('🤝 Client information'!Q114, "", IF(AND('🤝 Client information'!K114="yes", '🤝 Client information'!N114="yes"), "EMPLOYEE", IF(AND('🤝 Client information'!K114="yes", '🤝 Client information'!N114="no", '🤝 Client information'!H114="Finance & Accounting"), "CONTROLLER", IF(AND('🤝 Client information'!K114="yes", '🤝 Client information'!N114="no", '🤝 Client information'!H114<>"Finance & Accounting"), "FLEET_MGR", "")))) | N61: =IF(A61<>"",TODAY(),"") | S61: =IF(A61<>"","yes","") | U61: =IF(A61<>"",TODAY(),"")
A62: =IF('🤝 Client information'!Q115,"",IF('🤝 Client information'!K115="yes",'🤝 Client information'!C115,"")) | B62: =IF('🤝 Client information'!Q115,"",IF('🤝 Client information'!K115="yes",'🤝 Client information'!D115,"")) | C62: =IF('🤝 Client information'!Q115,"",IF('🤝 Client information'!K115="yes",'🤝 Client information'!F115,"")) | F62: =IF('🤝 Client information'!Q115,"",IF('🤝 Client information'!K115="yes",'🤝 Client information'!I115,"")) | G62: =IF('🤝 Client information'!Q115,"",IF('🤝 Client information'!K115="yes",'🤝 Client information'!J115,"")) | M62: =IF('🤝 Client information'!Q115, "", IF(AND('🤝 Client information'!K115="yes", '🤝 Client information'!N115="yes"), "EMPLOYEE", IF(AND('🤝 Client information'!K115="yes", '🤝 Client information'!N115="no", '🤝 Client information'!H115="Finance & Accounting"), "CONTROLLER", IF(AND('🤝 Client information'!K115="yes", '🤝 Client information'!N115="no", '🤝 Client information'!H115<>"Finance & Accounting"), "FLEET_MGR", "")))) | N62: =IF(A62<>"",TODAY(),"") | S62: =IF(A62<>"","yes","") | U62: =IF(A62<>"",TODAY(),"")
A63: =IF('🤝 Client information'!Q116,"",IF('🤝 Client information'!K116="yes",'🤝 Client information'!C116,"")) | B63: =IF('🤝 Client information'!Q116,"",IF('🤝 Client information'!K116="yes",'🤝 Client information'!D116,"")) | C63: =IF('🤝 Client information'!Q116,"",IF('🤝 Client information'!K116="yes",'🤝 Client information'!F116,"")) | F63: =IF('🤝 Client information'!Q116,"",IF('🤝 Client information'!K116="yes",'🤝 Client information'!I116,"")) | G63: =IF('🤝 Client information'!Q116,"",IF('🤝 Client information'!K116="yes",'🤝 Client information'!J116,"")) | M63: =IF('🤝 Client information'!Q116, "", IF(AND('🤝 Client information'!K116="yes", '🤝 Client information'!N116="yes"), "EMPLOYEE", IF(AND('🤝 Client information'!K116="yes", '🤝 Client information'!N116="no", '🤝 Client information'!H116="Finance & Accounting"), "CONTROLLER", IF(AND('🤝 Client information'!K116="yes", '🤝 Client information'!N116="no", '🤝 Client information'!H116<>"Finance & Accounting"), "FLEET_MGR", "")))) | N63: =IF(A63<>"",TODAY(),"") | S63: =IF(A63<>"","yes","") | U63: =IF(A63<>"",TODAY(),"")
A64: =IF('🤝 Client information'!Q117,"",IF('🤝 Client information'!K117="yes",'🤝 Client information'!C117,"")) | B64: =IF('🤝 Client information'!Q117,"",IF('🤝 Client information'!K117="yes",'🤝 Client information'!D117,"")) | C64: =IF('🤝 Client information'!Q117,"",IF('🤝 Client information'!K117="yes",'🤝 Client information'!F117,"")) | F64: =IF('🤝 Client information'!Q117,"",IF('🤝 Client information'!K117="yes",'🤝 Client information'!I117,"")) | G64: =IF('🤝 Client information'!Q117,"",IF('🤝 Client information'!K117="yes",'🤝 Client information'!J117,"")) | M64: =IF('🤝 Client information'!Q117, "", IF(AND('🤝 Client information'!K117="yes", '🤝 Client information'!N117="yes"), "EMPLOYEE", IF(AND('🤝 Client information'!K117="yes", '🤝 Client information'!N117="no", '🤝 Client information'!H117="Finance & Accounting"), "CONTROLLER", IF(AND('🤝 Client information'!K117="yes", '🤝 Client information'!N117="no", '🤝 Client information'!H117<>"Finance & Accounting"), "FLEET_MGR", "")))) | N64: =IF(A64<>"",TODAY(),"") | S64: =IF(A64<>"","yes","") | U64: =IF(A64<>"",TODAY(),"")
A65: =IF('🤝 Client information'!Q118,"",IF('🤝 Client information'!K118="yes",'🤝 Client information'!C118,"")) | B65: =IF('🤝 Client information'!Q118,"",IF('🤝 Client information'!K118="yes",'🤝 Client information'!D118,"")) | C65: =IF('🤝 Client information'!Q118,"",IF('🤝 Client information'!K118="yes",'🤝 Client information'!F118,"")) | F65: =IF('🤝 Client information'!Q118,"",IF('🤝 Client information'!K118="yes",'🤝 Client information'!I118,"")) | G65: =IF('🤝 Client information'!Q118,"",IF('🤝 Client information'!K118="yes",'🤝 Client information'!J118,"")) | M65: =IF('🤝 Client information'!Q118, "", IF(AND('🤝 Client information'!K118="yes", '🤝 Client information'!N118="yes"), "EMPLOYEE", IF(AND('🤝 Client information'!K118="yes", '🤝 Client information'!N118="no", '🤝 Client information'!H118="Finance & Accounting"), "CONTROLLER", IF(AND('🤝 Client information'!K118="yes", '🤝 Client information'!N118="no", '🤝 Client information'!H118<>"Finance & Accounting"), "FLEET_MGR", "")))) | N65: =IF(A65<>"",TODAY(),"") | S65: =IF(A65<>"","yes","") | U65: =IF(A65<>"",TODAY(),"")
A66: =IF('🤝 Client information'!Q119,"",IF('🤝 Client information'!K119="yes",'🤝 Client information'!C119,"")) | B66: =IF('🤝 Client information'!Q119,"",IF('🤝 Client information'!K119="yes",'🤝 Client information'!D119,"")) | C66: =IF('🤝 Client information'!Q119,"",IF('🤝 Client information'!K119="yes",'🤝 Client information'!F119,"")) | F66: =IF('🤝 Client information'!Q119,"",IF('🤝 Client information'!K119="yes",'🤝 Client information'!I119,"")) | G66: =IF('🤝 Client information'!Q119,"",IF('🤝 Client information'!K119="yes",'🤝 Client information'!J119,"")) | M66: =IF('🤝 Client information'!Q119, "", IF(AND('🤝 Client information'!K119="yes", '🤝 Client information'!N119="yes"), "EMPLOYEE", IF(AND('🤝 Client information'!K119="yes", '🤝 Client information'!N119="no", '🤝 Client information'!H119="Finance & Accounting"), "CONTROLLER", IF(AND('🤝 Client information'!K119="yes", '🤝 Client information'!N119="no", '🤝 Client information'!H119<>"Finance & Accounting"), "FLEET_MGR", "")))) | N66: =IF(A66<>"",TODAY(),"") | S66: =IF(A66<>"","yes","") | U66: =IF(A66<>"",TODAY(),"")
A67: =IF('🤝 Client information'!Q120,"",IF('🤝 Client information'!K120="yes",'🤝 Client information'!C120,"")) | B67: =IF('🤝 Client information'!Q120,"",IF('🤝 Client information'!K120="yes",'🤝 Client information'!D120,"")) | C67: =IF('🤝 Client information'!Q120,"",IF('🤝 Client information'!K120="yes",'🤝 Client information'!F120,"")) | F67: =IF('🤝 Client information'!Q120,"",IF('🤝 Client information'!K120="yes",'🤝 Client information'!I120,"")) | G67: =IF('🤝 Client information'!Q120,"",IF('🤝 Client information'!K120="yes",'🤝 Client information'!J120,"")) | M67: =IF('🤝 Client information'!Q120, "", IF(AND('🤝 Client information'!K120="yes", '🤝 Client information'!N120="yes"), "EMPLOYEE", IF(AND('🤝 Client information'!K120="yes", '🤝 Client information'!N120="no", '🤝 Client information'!H120="Finance & Accounting"), "CONTROLLER", IF(AND('🤝 Client information'!K120="yes", '🤝 Client information'!N120="no", '🤝 Client information'!H120<>"Finance & Accounting"), "FLEET_MGR", "")))) | N67: =IF(A67<>"",TODAY(),"") | S67: =IF(A67<>"","yes","") | U67: =IF(A67<>"",TODAY(),"")
A68: =IF('🤝 Client information'!Q121,"",IF('🤝 Client information'!K121="yes",'🤝 Client information'!C121,"")) | B68: =IF('🤝 Client information'!Q121,"",IF('🤝 Client information'!K121="yes",'🤝 Client information'!D121,"")) | C68: =IF('🤝 Client information'!Q121,"",IF('🤝 Client information'!K121="yes",'🤝 Client information'!F121,"")) | F68: =IF('🤝 Client information'!Q121,"",IF('🤝 Client information'!K121="yes",'🤝 Client information'!I121,"")) | G68: =IF('🤝 Client information'!Q121,"",IF('🤝 Client information'!K121="yes",'🤝 Client information'!J121,"")) | M68: =IF('🤝 Client information'!Q121, "", IF(AND('🤝 Client information'!K121="yes", '🤝 Client information'!N121="yes"), "EMPLOYEE", IF(AND('🤝 Client information'!K121="yes", '🤝 Client information'!N121="no", '🤝 Client information'!H121="Finance & Accounting"), "CONTROLLER", IF(AND('🤝 Client information'!K121="yes", '🤝 Client information'!N121="no", '🤝 Client information'!H121<>"Finance & Accounting"), "FLEET_MGR", "")))) | N68: =IF(A68<>"",TODAY(),"") | S68: =IF(A68<>"","yes","") | U68: =IF(A68<>"",TODAY(),"")
A69: =IF('🤝 Client information'!Q122,"",IF('🤝 Client information'!K122="yes",'🤝 Client information'!C122,"")) | B69: =IF('🤝 Client information'!Q122,"",IF('🤝 Client information'!K122="yes",'🤝 Client information'!D122,"")) | C69: =IF('🤝 Client information'!Q122,"",IF('🤝 Client information'!K122="yes",'🤝 Client information'!F122,"")) | F69: =IF('🤝 Client information'!Q122,"",IF('🤝 Client information'!K122="yes",'🤝 Client information'!I122,"")) | G69: =IF('🤝 Client information'!Q122,"",IF('🤝 Client information'!K122="yes",'🤝 Client information'!J122,"")) | M69: =IF('🤝 Client information'!Q122, "", IF(AND('🤝 Client information'!K122="yes", '🤝 Client information'!N122="yes"), "EMPLOYEE", IF(AND('🤝 Client information'!K122="yes", '🤝 Client information'!N122="no", '🤝 Client information'!H122="Finance & Accounting"), "CONTROLLER", IF(AND('🤝 Client information'!K122="yes", '🤝 Client information'!N122="no", '🤝 Client information'!H122<>"Finance & Accounting"), "FLEET_MGR", "")))) | N69: =IF(A69<>"",TODAY(),"") | S69: =IF(A69<>"","yes","") | U69: =IF(A69<>"",TODAY(),"")
A70: =IF('🤝 Client information'!Q123,"",IF('🤝 Client information'!K123="yes",'🤝 Client information'!C123,"")) | B70: =IF('🤝 Client information'!Q123,"",IF('🤝 Client information'!K123="yes",'🤝 Client information'!D123,"")) | C70: =IF('🤝 Client information'!Q123,"",IF('🤝 Client information'!K123="yes",'🤝 Client information'!F123,"")) | F70: =IF('🤝 Client information'!Q123,"",IF('🤝 Client information'!K123="yes",'🤝 Client information'!I123,"")) | G70: =IF('🤝 Client information'!Q123,"",IF('🤝 Client information'!K123="yes",'🤝 Client information'!J123,"")) | M70: =IF('🤝 Client information'!Q123, "", IF(AND('🤝 Client information'!K123="yes", '🤝 Client information'!N123="yes"), "EMPLOYEE", IF(AND('🤝 Client information'!K123="yes", '🤝 Client information'!N123="no", '🤝 Client information'!H123="Finance & Accounting"), "CONTROLLER", IF(AND('🤝 Client information'!K123="yes", '🤝 Client information'!N123="no", '🤝 Client information'!H123<>"Finance & Accounting"), "FLEET_MGR", "")))) | N70: =IF(A70<>"",TODAY(),"") | S70: =IF(A70<>"","yes","") | U70: =IF(A70<>"",TODAY(),"")
... A73: =IF('🤝 Client information'!Q126,"",IF('🤝 Client information'!K126="yes",'🤝 Client information'!C126,"")) | B73: =IF('🤝 Client information'!Q126,"",IF('🤝 Client information'!K126="yes",'🤝 Client information'!D126,"")) | C73: =IF('🤝 Client information'!Q126,"",IF('🤝 Client information'!K126="yes",'🤝 Client information'!F126,"")) | F73: =IF('🤝 Client information'!Q126,"",IF('🤝 Client information'!K126="yes",'🤝 Client information'!I126,"")) | G73: =IF('🤝 Client information'!Q126,"",IF('🤝 Client information'!K126="yes",'🤝 Client information'!J126,"")) | M73: =IF('🤝 Client information'!Q126, "", IF(AND('🤝 Client information'!K126="yes", '🤝 Client information'!N126="yes"), "EMPLOYEE", IF(AND('🤝 Client information'!K126="yes", '🤝 Client information'!N126="no", '🤝 Client information'!H126="Finance & Accounting"), "CONTROLLER", IF(AND('🤝 Client information'!K126="yes", '🤝 Client information'!N126="no", '🤝 Client information'!H126<>"Finance & Accounting"), "FLEET_MGR", "")))) | N73: =IF(A73<>"",TODAY(),"") | S73: =IF(A73<>"","yes","") | U73: =IF(A73<>"",TODAY(),"")
